3_Intermediate_Combinational/Basic_ALU/alu_beh.v
module alu_beh(input a,b,input [1:0]sel,output reg y);
always @ (*) begin
case(sel)
2'b00 : y=a+b;
2'b01 : y=a-b;
2'b10 : y=a&b;
2'b11 : y=a|b;
endcase
end
endmodule

3_Intermediate_Combinational/Basic_ALU/alu_tb.v
module alu_tb;
reg a,b;
reg [1:0]sel;
wire y;

alu_beh uut(.a(a),.b(b),.sel(sel),.y(y));

integer i;
initial
begin
$dumpfile("alu.vcd");
$dumpvars(0,alu_tb);
$monitor("time=%0t,a=%b,b=%b,sel=%b,y=%b",$time,a,b,sel,y);
for(i=0;i<16;i=i+1)
begin
{a,b,sel}=i;
#10;
end
end
endmodule

3_Intermediate_Combinational/Basic_ALU/alu.vcd
$date
	Wed Jun 17 04:32:02 2026
$end
$version
	Icarus Verilog
$end
$timescale
	1s
$end
$scope module alu_tb $end
$var wire 1 ! y $end
$var reg 1 " a $end
$var reg 1 # b $end
$var reg 2 $ sel [1:0] $end
$var integer 32 % i [31:0] $end
$scope module uut $end
$var wire 1 " a $end
$var wire 1 # b $end
$var wire 2 & sel [1:0] $end
$var reg 1 ! y $end
$upscope $end
$upscope $end
$enddefinitions $end
$comment Show the parameter values. $end
$dumpall
$end
#0
$dumpvars
b0 &
b0 %
b0 $
0#
0"
0!
$end
#10
b1 $
b1 &
b1 %
#20
b10 $
b10 &
b10 %
#30
b11 $
b11 &
b11 %
#40
1!
1#
b0 $
b0 &
b100 %
#50
b1 $
b1 &
b101 %
#60
0!
b10 $
b10 &
b110 %
#70
1!
b11 $
b11 &
b111 %
#80
1"
0#
b0 $
b0 &
b1000 %
#90
b1 $
b1 &
b1001 %
#100
0!
b10 $
b10 &
b1010 %
#110
1!
b11 $
b11 &
b1011 %
#120
0!
1#
b0 $
b0 &
b1100 %
#130
b1 $
b1 &
b1101 %
#140
1!
b10 $
b10 &
b1110 %
#150
b11 $
b11 &
b1111 %
#160
b10000 %
