3_Intermediate_Combinational/Comparator_2bit/fourbitcompare_data_always_if.v
module fourbitcompare_data_always_if(input [1:0]a,input [1:0]b,output reg g,e,l);
always @(*) begin
	if(a>b)
	begin
		g=1;e=0;l=0;
	end
	else if(a<b)
	begin
		g=0;e=0;l=1;
	end
	else if(a==b)
	begin
		g=0;e=1;l=0;
	end
	else
	begin
		g=0;e=0;l=0;
	end
end
endmodule

3_Intermediate_Combinational/Comparator_2bit/fourbitcompare_tb.v
module fourbitcompare_tb;
reg [1:0]a;
reg [1:0]b;

wire g,e,l;

fourbitcompare_data_always_if uut(.a(a),.b(b),.g(g),.e(e),.l(l));

integer i;

initial begin
$dumpfile("fourbitcompare.vcd");
$dumpvars(0,fourbitcompare_tb);

$monitor("time=%0t,a=%b%b,b=%b%b,g=%b,e=%b,l=%b",$time,a[1],a[0],b[1],b[0],g,e,l);

for(i=0;i<16;i=i+1)begin
{a,b}=i;
#10;
end
$finish;
end
endmodule

3_Intermediate_Combinational/Comparator_2bit/fourbitcompare.vcd
$date
	Tue Jun  9 09:35:53 2026
$end
$version
	Icarus Verilog
$end
$timescale
	1s
$end
$scope module fourbitcompare_tb $end
$var wire 1 ! l $end
$var wire 1 " g $end
$var wire 1 # e $end
$var reg 2 $ a [1:0] $end
$var reg 2 % b [1:0] $end
$var integer 32 & i [31:0] $end
$scope module uut $end
$var wire 2 ' a [1:0] $end
$var wire 2 ( b [1:0] $end
$var reg 1 # e $end
$var reg 1 " g $end
$var reg 1 ! l $end
$upscope $end
$upscope $end
$enddefinitions $end
$comment Show the parameter values. $end
$dumpall
$end
#0
$dumpvars
b0 (
b0 '
b0 &
b0 %
b0 $
1#
0"
0!
$end
#10
1!
0#
b1 %
b1 (
b1 &
#20
b10 %
b10 (
b10 &
#30
b11 %
b11 (
b11 &
#40
0!
1"
b1 $
b1 '
b0 %
b0 (
b100 &
#50
1#
0"
b1 %
b1 (
b101 &
#60
1!
0#
b10 %
b10 (
b110 &
#70
b11 %
b11 (
b111 &
#80
0!
1"
b10 $
b10 '
b0 %
b0 (
b1000 &
#90
b1 %
b1 (
b1001 &
#100
1#
0"
b10 %
b10 (
b1010 &
#110
1!
0#
b11 %
b11 (
b1011 &
#120
0!
1"
b11 $
b11 '
b0 %
b0 (
b1100 &
#130
b1 %
b1 (
b1101 &
#140
b10 %
b10 (
b1110 &
#150
1#
0"
b11 %
b11 (
b1111 &
#160
b10000 &
