combinational-2/priority_encoder/priority_encoder_if_else.v
module priority_encoder_if_else (
    input  [3:0] D,
    output reg [1:0]  Y
);

always @(*) begin
    if (D[3])
        Y = 2'b11;
    else if (D[2])
        Y = 2'b10;
    else if (D[1])
        Y = 2'b01;
    else if (D[0])
        Y = 2'b00;
    else
        Y = 2'b00;
end

endmodule

combinational-2/priority_encoder/priority_encoder_tb.v
module priority_encoder_tb;

reg [3:0] D;
wire [1:0] Y;

priority_encoder_if_else dut (
    .D(D),
    .Y(Y)
);

initial begin

    $dumpfile("p_encoder.vcd");
    $dumpvars(0,priority_encoder_tb);
    $monitor("Time=%0t D=%b Y=%b", $time, D, Y);

    D = 4'b0000; #10;
    D = 4'b0001; #10;
    D = 4'b0010; #10;
    D = 4'b0100; #10;
    D = 4'b1000; #10;
    D = 4'b0011; #10;
    D = 4'b0111; #10;
    D = 4'b1111; #10;


    $finish;
end

endmodule

combinational-2/priority_encoder/p_encoder.vcd
$date
	Wed Jun 10 03:45:32 2026
$end
$version
	Icarus Verilog
$end
$timescale
	1s
$end
$scope module priority_encoder_tb $end
$var wire 2 ! Y [1:0] $end
$var reg 4 " D [3:0] $end
$scope module dut $end
$var wire 4 # D [3:0] $end
$var reg 2 $ Y [1:0] $end
$upscope $end
$upscope $end
$enddefinitions $end
$comment Show the parameter values. $end
$dumpall
$end
#0
$dumpvars
b0 $
b0 #
b0 "
b0 !
$end
#10
b1 "
b1 #
#20
b1 !
b1 $
b10 "
b10 #
#30
b10 !
b10 $
b100 "
b100 #
#40
b11 !
b11 $
b1000 "
b1000 #
#50
b1 !
b1 $
b11 "
b11 #
#60
b10 !
b10 $
b111 "
b111 #
#70
b11 !
b11 $
b1111 "
b1111 #
