3_Intermediate_Combinational/Binary_to_Gray/Binary_to_gray_data.v
module Binary_to_gray_data#(parameter N=4)(input [N-1:0]a,output [N-1:0]y);


genvar i;


assign y[N-1] = a[N-1];

generate
for(i=0; i<N-1; i=i+1)
begin : gray
assign y[i]=a[i]^a[i+1];
end
endgenerate
endmodule

3_Intermediate_Combinational/Binary_to_Gray/Binary_to_gray_tb.v
module Binary_to_gray_tb;

reg [9:0] a;
wire [9:0]y;

Binary_to_gray_data#(10) uut(.a(a),.y(y));


integer i;

initial
begin
$dumpfile("Binary_to_gray.vcd");
$dumpvars(0,Binary_to_gray_tb);
$monitor("t=%0t | a=%b | y=%b",$time,a,y);

for(i=0;i<1024;i=i+1)begin
a=i;
#3;
end

$finish;

end

endmodule

3_Intermediate_Combinational/Binary_to_Gray/Binary_to_gray.vcd
$date
	Mon Jun 15 09:34:16 2026
$end
$version
	Icarus Verilog
$end
$timescale
	1s
$end
$scope module Binary_to_gray_tb $end
$var wire 10 ! y [9:0] $end
$var reg 10 " a [9:0] $end
$var integer 32 # i [31:0] $end
$scope module uut $end
$var wire 10 $ a [9:0] $end
$var wire 10 % y [9:0] $end
$var parameter 32 & N $end
$scope begin gray[0] $end
$var parameter 2 ' i $end
$upscope $end
$scope begin gray[1] $end
$var parameter 2 ( i $end
$upscope $end
$scope begin gray[2] $end
$var parameter 3 ) i $end
$upscope $end
$scope begin gray[3] $end
$var parameter 3 * i $end
$upscope $end
$scope begin gray[4] $end
$var parameter 4 + i $end
$upscope $end
$scope begin gray[5] $end
$var parameter 4 , i $end
$upscope $end
$scope begin gray[6] $end
$var parameter 4 - i $end
$upscope $end
$scope begin gray[7] $end
$var parameter 4 . i $end
$upscope $end
$scope begin gray[8] $end
$var parameter 5 / i $end
$upscope $end
$upscope $end
$upscope $end
$enddefinitions $end
$comment Show the parameter values. $end
$dumpall
b1000 /
b111 .
b110 -
b101 ,
b100 +
b11 *
b10 )
b1 (
b0 '
b1010 &
$end
#0
$dumpvars
b0 %
b0 $
b0 #
b0 "
b0 !
$end
#3
b1 !
b1 %
b1 "
b1 $
b1 #
#6
b11 !
b11 %
b10 "
b10 $
b10 #
#9
b10 !
b10 %
b11 "
b11 $
b11 #
#12
b110 !
b110 %
b100 "
b100 $
b100 #
#15
b111 !
b111 %
b101 "
b101 $
b101 #
#18
b101 !
b101 %
b110 "
b110 $
b110 #
#21
b100 !
b100 %
b111 "
b111 $
b111 #
#24
b1100 !
b1100 %
b1000 "
b1000 $
b1000 #
#27
b1101 !
b1101 %
b1001 "
b1001 $
b1001 #
#30
b1111 !
b1111 %
b1010 "
b1010 $
b1010 #
#33
b1110 !
b1110 %
b1011 "
b1011 $
b1011 #
#36
b1010 !
b1010 %
b1100 "
b1100 $
b1100 #
#39
b1011 !
b1011 %
b1101 "
b1101 $
b1101 #
#42
b1001 !
b1001 %
b1110 "
b1110 $
b1110 #
#45
b1000 !
b1000 %
b1111 "
b1111 $
b1111 #
#48
b11000 !
b11000 %
b10000 "
b10000 $
b10000 #
#51
b11001 !
b11001 %
b10001 "
b10001 $
b10001 #
#54
b11011 !
b11011 %
b10010 "
b10010 $
b10010 #
#57
b11010 !
b11010 %
b10011 "
b10011 $
b10011 #
#60
b11110 !
b11110 %
b10100 "
b10100 $
b10100 #
#63
b11111 !
b11111 %
b10101 "
b10101 $
b10101 #
#66
b11101 !
b11101 %
b10110 "
b10110 $
b10110 #
#69
b11100 !
b11100 %
b10111 "
b10111 $
b10111 #
#72
b10100 !
b10100 %
b11000 "
b11000 $
b11000 #
#75
b10101 !
b10101 %
b11001 "
b11001 $
b11001 #
#78
b10111 !
b10111 %
b11010 "
b11010 $
b11010 #
#81
b10110 !
b10110 %
b11011 "
b11011 $
b11011 #
#84
b10010 !
b10010 %
b11100 "
b11100 $
b11100 #
#87
b10011 !
b10011 %
b11101 "
b11101 $
b11101 #
#90
b10001 !
b10001 %
b11110 "
b11110 $
b11110 #
#93
b10000 !
b10000 %
b11111 "
b11111 $
b11111 #
#96
b110000 !
b110000 %
b100000 "
b100000 $
b100000 #
#99
b110001 !
b110001 %
b100001 "
b100001 $
b100001 #
#102
b110011 !
b110011 %
b100010 "
b100010 $
b100010 #
#105
b110010 !
b110010 %
b100011 "
b100011 $
b100011 #
#108
b110110 !
b110110 %
b100100 "
b100100 $
b100100 #
#111
b110111 !
b110111 %
b100101 "
b100101 $
b100101 #
#114
b110101 !
b110101 %
b100110 "
b100110 $
b100110 #
#117
b110100 !
b110100 %
b100111 "
b100111 $
b100111 #
#120
b111100 !
b111100 %
b101000 "
b101000 $
b101000 #
#123
b111101 !
b111101 %
b101001 "
b101001 $
b101001 #
#126
b111111 !
b111111 %
b101010 "
b101010 $
b101010 #
#129
b111110 !
b111110 %
b101011 "
b101011 $
b101011 #
#132
b111010 !
b111010 %
b101100 "
b101100 $
b101100 #
#135
b111011 !
b111011 %
b101101 "
b101101 $
b101101 #
#138
b111001 !
b111001 %
b101110 "
b101110 $
b101110 #
#141
b111000 !
b111000 %
b101111 "
b101111 $
b101111 #
#144
b101000 !
b101000 %
b110000 "
b110000 $
b110000 #
#147
b101001 !
b101001 %
b110001 "
b110001 $
b110001 #
#150
b101011 !
b101011 %
b110010 "
b110010 $
b110010 #
#153
b101010 !
b101010 %
b110011 "
b110011 $
b110011 #
#156
b101110 !
b101110 %
b110100 "
b110100 $
b110100 #
#159
b101111 !
b101111 %
b110101 "
b110101 $
b110101 #
#162
b101101 !
b101101 %
b110110 "
b110110 $
b110110 #
#165
b101100 !
b101100 %
b110111 "
b110111 $
b110111 #
#168
b100100 !
b100100 %
b111000 "
b111000 $
b111000 #
#171
b100101 !
b100101 %
b111001 "
b111001 $
b111001 #
#174
b100111 !
b100111 %
b111010 "
b111010 $
b111010 #
#177
b100110 !
b100110 %
b111011 "
b111011 $
b111011 #
#180
b100010 !
b100010 %
b111100 "
b111100 $
b111100 #
#183
b100011 !
b100011 %
b111101 "
b111101 $
b111101 #
#186
b100001 !
b100001 %
b111110 "
b111110 $
b111110 #
#189
b100000 !
b100000 %
b111111 "
b111111 $
b111111 #
#192
b1100000 !
b1100000 %
b1000000 "
b1000000 $
b1000000 #
#195
b1100001 !
b1100001 %
b1000001 "
b1000001 $
b1000001 #
#198
b1100011 !
b1100011 %
b1000010 "
b1000010 $
b1000010 #
#201
b1100010 !
b1100010 %
b1000011 "
b1000011 $
b1000011 #
#204
b1100110 !
b1100110 %
b1000100 "
b1000100 $
b1000100 #
#207
b1100111 !
b1100111 %
b1000101 "
b1000101 $
b1000101 #
#210
b1100101 !
b1100101 %
b1000110 "
b1000110 $
b1000110 #
#213
b1100100 !
b1100100 %
b1000111 "
b1000111 $
b1000111 #
#216
b1101100 !
b1101100 %
b1001000 "
b1001000 $
b1001000 #
#219
b1101101 !
b1101101 %
b1001001 "
b1001001 $
b1001001 #
#222
b1101111 !
b1101111 %
b1001010 "
b1001010 $
b1001010 #
#225
b1101110 !
b1101110 %
b1001011 "
b1001011 $
b1001011 #
#228
b1101010 !
b1101010 %
b1001100 "
b1001100 $
b1001100 #
#231
b1101011 !
b1101011 %
b1001101 "
b1001101 $
b1001101 #
#234
b1101001 !
b1101001 %
b1001110 "
b1001110 $
b1001110 #
#237
b1101000 !
b1101000 %
b1001111 "
b1001111 $
b1001111 #
#240
b1111000 !
b1111000 %
b1010000 "
b1010000 $
b1010000 #
#243
b1111001 !
b1111001 %
b1010001 "
b1010001 $
b1010001 #
#246
b1111011 !
b1111011 %
b1010010 "
b1010010 $
b1010010 #
#249
b1111010 !
b1111010 %
b1010011 "
b1010011 $
b1010011 #
#252
b1111110 !
b1111110 %
b1010100 "
b1010100 $
b1010100 #
#255
b1111111 !
b1111111 %
b1010101 "
b1010101 $
b1010101 #
#258
b1111101 !
b1111101 %
b1010110 "
b1010110 $
b1010110 #
#261
b1111100 !
b1111100 %
b1010111 "
b1010111 $
b1010111 #
#264
b1110100 !
b1110100 %
b1011000 "
b1011000 $
b1011000 #
#267
b1110101 !
b1110101 %
b1011001 "
b1011001 $
b1011001 #
#270
b1110111 !
b1110111 %
b1011010 "
b1011010 $
b1011010 #
#273
b1110110 !
b1110110 %
b1011011 "
b1011011 $
b1011011 #
#276
b1110010 !
b1110010 %
b1011100 "
b1011100 $
b1011100 #
#279
b1110011 !
b1110011 %
b1011101 "
b1011101 $
b1011101 #
#282
b1110001 !
b1110001 %
b1011110 "
b1011110 $
b1011110 #
#285
b1110000 !
b1110000 %
b1011111 "
b1011111 $
b1011111 #
#288
b1010000 !
b1010000 %
b1100000 "
b1100000 $
b1100000 #
#291
b1010001 !
b1010001 %
b1100001 "
b1100001 $
b1100001 #
#294
b1010011 !
b1010011 %
b1100010 "
b1100010 $
b1100010 #
#297
b1010010 !
b1010010 %
b1100011 "
b1100011 $
b1100011 #
#300
b1010110 !
b1010110 %
b1100100 "
b1100100 $
b1100100 #
#303
b1010111 !
b1010111 %
b1100101 "
b1100101 $
b1100101 #
#306
b1010101 !
b1010101 %
b1100110 "
b1100110 $
b1100110 #
#309
b1010100 !
b1010100 %
b1100111 "
b1100111 $
b1100111 #
#312
b1011100 !
b1011100 %
b1101000 "
b1101000 $
b1101000 #
#315
b1011101 !
b1011101 %
b1101001 "
b1101001 $
b1101001 #
#318
b1011111 !
b1011111 %
b1101010 "
b1101010 $
b1101010 #
#321
b1011110 !
b1011110 %
b1101011 "
b1101011 $
b1101011 #
#324
b1011010 !
b1011010 %
b1101100 "
b1101100 $
b1101100 #
#327
b1011011 !
b1011011 %
b1101101 "
b1101101 $
b1101101 #
#330
b1011001 !
b1011001 %
b1101110 "
b1101110 $
b1101110 #
#333
b1011000 !
b1011000 %
b1101111 "
b1101111 $
b1101111 #
#336
b1001000 !
b1001000 %
b1110000 "
b1110000 $
b1110000 #
#339
b1001001 !
b1001001 %
b1110001 "
b1110001 $
b1110001 #
#342
b1001011 !
b1001011 %
b1110010 "
b1110010 $
b1110010 #
#345
b1001010 !
b1001010 %
b1110011 "
b1110011 $
b1110011 #
#348
b1001110 !
b1001110 %
b1110100 "
b1110100 $
b1110100 #
#351
b1001111 !
b1001111 %
b1110101 "
b1110101 $
b1110101 #
#354
b1001101 !
b1001101 %
b1110110 "
b1110110 $
b1110110 #
#357
b1001100 !
b1001100 %
b1110111 "
b1110111 $
b1110111 #
#360
b1000100 !
b1000100 %
b1111000 "
b1111000 $
b1111000 #
#363
b1000101 !
b1000101 %
b1111001 "
b1111001 $
b1111001 #
#366
b1000111 !
b1000111 %
b1111010 "
b1111010 $
b1111010 #
#369
b1000110 !
b1000110 %
b1111011 "
b1111011 $
b1111011 #
#372
b1000010 !
b1000010 %
b1111100 "
b1111100 $
b1111100 #
#375
b1000011 !
b1000011 %
b1111101 "
b1111101 $
b1111101 #
#378
b1000001 !
b1000001 %
b1111110 "
b1111110 $
b1111110 #
#381
b1000000 !
b1000000 %
b1111111 "
b1111111 $
b1111111 #
#384
b11000000 !
b11000000 %
b10000000 "
b10000000 $
b10000000 #
#387
b11000001 !
b11000001 %
b10000001 "
b10000001 $
b10000001 #
#390
b11000011 !
b11000011 %
b10000010 "
b10000010 $
b10000010 #
#393
b11000010 !
b11000010 %
b10000011 "
b10000011 $
b10000011 #
#396
b11000110 !
b11000110 %
b10000100 "
b10000100 $
b10000100 #
#399
b11000111 !
b11000111 %
b10000101 "
b10000101 $
b10000101 #
#402
b11000101 !
b11000101 %
b10000110 "
b10000110 $
b10000110 #
#405
b11000100 !
b11000100 %
b10000111 "
b10000111 $
b10000111 #
#408
b11001100 !
b11001100 %
b10001000 "
b10001000 $
b10001000 #
#411
b11001101 !
b11001101 %
b10001001 "
b10001001 $
b10001001 #
#414
b11001111 !
b11001111 %
b10001010 "
b10001010 $
b10001010 #
#417
b11001110 !
b11001110 %
b10001011 "
b10001011 $
b10001011 #
#420
b11001010 !
b11001010 %
b10001100 "
b10001100 $
b10001100 #
#423
b11001011 !
b11001011 %
b10001101 "
b10001101 $
b10001101 #
#426
b11001001 !
b11001001 %
b10001110 "
b10001110 $
b10001110 #
#429
b11001000 !
b11001000 %
b10001111 "
b10001111 $
b10001111 #
#432
b11011000 !
b11011000 %
b10010000 "
b10010000 $
b10010000 #
#435
b11011001 !
b11011001 %
b10010001 "
b10010001 $
b10010001 #
#438
b11011011 !
b11011011 %
b10010010 "
b10010010 $
b10010010 #
#441
b11011010 !
b11011010 %
b10010011 "
b10010011 $
b10010011 #
#444
b11011110 !
b11011110 %
b10010100 "
b10010100 $
b10010100 #
#447
b11011111 !
b11011111 %
b10010101 "
b10010101 $
b10010101 #
#450
b11011101 !
b11011101 %
b10010110 "
b10010110 $
b10010110 #
#453
b11011100 !
b11011100 %
b10010111 "
b10010111 $
b10010111 #
#456
b11010100 !
b11010100 %
b10011000 "
b10011000 $
b10011000 #
#459
b11010101 !
b11010101 %
b10011001 "
b10011001 $
b10011001 #
#462
b11010111 !
b11010111 %
b10011010 "
b10011010 $
b10011010 #
#465
b11010110 !
b11010110 %
b10011011 "
b10011011 $
b10011011 #
#468
b11010010 !
b11010010 %
b10011100 "
b10011100 $
b10011100 #
#471
b11010011 !
b11010011 %
b10011101 "
b10011101 $
b10011101 #
#474
b11010001 !
b11010001 %
b10011110 "
b10011110 $
b10011110 #
#477
b11010000 !
b11010000 %
b10011111 "
b10011111 $
b10011111 #
#480
b11110000 !
b11110000 %
b10100000 "
b10100000 $
b10100000 #
#483
b11110001 !
b11110001 %
b10100001 "
b10100001 $
b10100001 #
#486
b11110011 !
b11110011 %
b10100010 "
b10100010 $
b10100010 #
#489
b11110010 !
b11110010 %
b10100011 "
b10100011 $
b10100011 #
#492
b11110110 !
b11110110 %
b10100100 "
b10100100 $
b10100100 #
#495
b11110111 !
b11110111 %
b10100101 "
b10100101 $
b10100101 #
#498
b11110101 !
b11110101 %
b10100110 "
b10100110 $
b10100110 #
#501
b11110100 !
b11110100 %
b10100111 "
b10100111 $
b10100111 #
#504
b11111100 !
b11111100 %
b10101000 "
b10101000 $
b10101000 #
#507
b11111101 !
b11111101 %
b10101001 "
b10101001 $
b10101001 #
#510
b11111111 !
b11111111 %
b10101010 "
b10101010 $
b10101010 #
#513
b11111110 !
b11111110 %
b10101011 "
b10101011 $
b10101011 #
#516
b11111010 !
b11111010 %
b10101100 "
b10101100 $
b10101100 #
#519
b11111011 !
b11111011 %
b10101101 "
b10101101 $
b10101101 #
#522
b11111001 !
b11111001 %
b10101110 "
b10101110 $
b10101110 #
#525
b11111000 !
b11111000 %
b10101111 "
b10101111 $
b10101111 #
#528
b11101000 !
b11101000 %
b10110000 "
b10110000 $
b10110000 #
#531
b11101001 !
b11101001 %
b10110001 "
b10110001 $
b10110001 #
#534
b11101011 !
b11101011 %
b10110010 "
b10110010 $
b10110010 #
#537
b11101010 !
b11101010 %
b10110011 "
b10110011 $
b10110011 #
#540
b11101110 !
b11101110 %
b10110100 "
b10110100 $
b10110100 #
#543
b11101111 !
b11101111 %
b10110101 "
b10110101 $
b10110101 #
#546
b11101101 !
b11101101 %
b10110110 "
b10110110 $
b10110110 #
#549
b11101100 !
b11101100 %
b10110111 "
b10110111 $
b10110111 #
#552
b11100100 !
b11100100 %
b10111000 "
b10111000 $
b10111000 #
#555
b11100101 !
b11100101 %
b10111001 "
b10111001 $
b10111001 #
#558
b11100111 !
b11100111 %
b10111010 "
b10111010 $
b10111010 #
#561
b11100110 !
b11100110 %
b10111011 "
b10111011 $
b10111011 #
#564
b11100010 !
b11100010 %
b10111100 "
b10111100 $
b10111100 #
#567
b11100011 !
b11100011 %
b10111101 "
b10111101 $
b10111101 #
#570
b11100001 !
b11100001 %
b10111110 "
b10111110 $
b10111110 #
#573
b11100000 !
b11100000 %
b10111111 "
b10111111 $
b10111111 #
#576
b10100000 !
b10100000 %
b11000000 "
b11000000 $
b11000000 #
#579
b10100001 !
b10100001 %
b11000001 "
b11000001 $
b11000001 #
#582
b10100011 !
b10100011 %
b11000010 "
b11000010 $
b11000010 #
#585
b10100010 !
b10100010 %
b11000011 "
b11000011 $
b11000011 #
#588
b10100110 !
b10100110 %
b11000100 "
b11000100 $
b11000100 #
#591
b10100111 !
b10100111 %
b11000101 "
b11000101 $
b11000101 #
#594
b10100101 !
b10100101 %
b11000110 "
b11000110 $
b11000110 #
#597
b10100100 !
b10100100 %
b11000111 "
b11000111 $
b11000111 #
#600
b10101100 !
b10101100 %
b11001000 "
b11001000 $
b11001000 #
#603
b10101101 !
b10101101 %
b11001001 "
b11001001 $
b11001001 #
#606
b10101111 !
b10101111 %
b11001010 "
b11001010 $
b11001010 #
#609
b10101110 !
b10101110 %
b11001011 "
b11001011 $
b11001011 #
#612
b10101010 !
b10101010 %
b11001100 "
b11001100 $
b11001100 #
#615
b10101011 !
b10101011 %
b11001101 "
b11001101 $
b11001101 #
#618
b10101001 !
b10101001 %
b11001110 "
b11001110 $
b11001110 #
#621
b10101000 !
b10101000 %
b11001111 "
b11001111 $
b11001111 #
#624
b10111000 !
b10111000 %
b11010000 "
b11010000 $
b11010000 #
#627
b10111001 !
b10111001 %
b11010001 "
b11010001 $
b11010001 #
#630
b10111011 !
b10111011 %
b11010010 "
b11010010 $
b11010010 #
#633
b10111010 !
b10111010 %
b11010011 "
b11010011 $
b11010011 #
#636
b10111110 !
b10111110 %
b11010100 "
b11010100 $
b11010100 #
#639
b10111111 !
b10111111 %
b11010101 "
b11010101 $
b11010101 #
#642
b10111101 !
b10111101 %
b11010110 "
b11010110 $
b11010110 #
#645
b10111100 !
b10111100 %
b11010111 "
b11010111 $
b11010111 #
#648
b10110100 !
b10110100 %
b11011000 "
b11011000 $
b11011000 #
#651
b10110101 !
b10110101 %
b11011001 "
b11011001 $
b11011001 #
#654
b10110111 !
b10110111 %
b11011010 "
b11011010 $
b11011010 #
#657
b10110110 !
b10110110 %
b11011011 "
b11011011 $
b11011011 #
#660
b10110010 !
b10110010 %
b11011100 "
b11011100 $
b11011100 #
#663
b10110011 !
b10110011 %
b11011101 "
b11011101 $
b11011101 #
#666
b10110001 !
b10110001 %
b11011110 "
b11011110 $
b11011110 #
#669
b10110000 !
b10110000 %
b11011111 "
b11011111 $
b11011111 #
#672
b10010000 !
b10010000 %
b11100000 "
b11100000 $
b11100000 #
#675
b10010001 !
b10010001 %
b11100001 "
b11100001 $
b11100001 #
#678
b10010011 !
b10010011 %
b11100010 "
b11100010 $
b11100010 #
#681
b10010010 !
b10010010 %
b11100011 "
b11100011 $
b11100011 #
#684
b10010110 !
b10010110 %
b11100100 "
b11100100 $
b11100100 #
#687
b10010111 !
b10010111 %
b11100101 "
b11100101 $
b11100101 #
#690
b10010101 !
b10010101 %
b11100110 "
b11100110 $
b11100110 #
#693
b10010100 !
b10010100 %
b11100111 "
b11100111 $
b11100111 #
#696
b10011100 !
b10011100 %
b11101000 "
b11101000 $
b11101000 #
#699
b10011101 !
b10011101 %
b11101001 "
b11101001 $
b11101001 #
#702
b10011111 !
b10011111 %
b11101010 "
b11101010 $
b11101010 #
#705
b10011110 !
b10011110 %
b11101011 "
b11101011 $
b11101011 #
#708
b10011010 !
b10011010 %
b11101100 "
b11101100 $
b11101100 #
#711
b10011011 !
b10011011 %
b11101101 "
b11101101 $
b11101101 #
#714
b10011001 !
b10011001 %
b11101110 "
b11101110 $
b11101110 #
#717
b10011000 !
b10011000 %
b11101111 "
b11101111 $
b11101111 #
#720
b10001000 !
b10001000 %
b11110000 "
b11110000 $
b11110000 #
#723
b10001001 !
b10001001 %
b11110001 "
b11110001 $
b11110001 #
#726
b10001011 !
b10001011 %
b11110010 "
b11110010 $
b11110010 #
#729
b10001010 !
b10001010 %
b11110011 "
b11110011 $
b11110011 #
#732
b10001110 !
b10001110 %
b11110100 "
b11110100 $
b11110100 #
#735
b10001111 !
b10001111 %
b11110101 "
b11110101 $
b11110101 #
#738
b10001101 !
b10001101 %
b11110110 "
b11110110 $
b11110110 #
#741
b10001100 !
b10001100 %
b11110111 "
b11110111 $
b11110111 #
#744
b10000100 !
b10000100 %
b11111000 "
b11111000 $
b11111000 #
#747
b10000101 !
b10000101 %
b11111001 "
b11111001 $
b11111001 #
#750
b10000111 !
b10000111 %
b11111010 "
b11111010 $
b11111010 #
#753
b10000110 !
b10000110 %
b11111011 "
b11111011 $
b11111011 #
#756
b10000010 !
b10000010 %
b11111100 "
b11111100 $
b11111100 #
#759
b10000011 !
b10000011 %
b11111101 "
b11111101 $
b11111101 #
#762
b10000001 !
b10000001 %
b11111110 "
b11111110 $
b11111110 #
#765
b10000000 !
b10000000 %
b11111111 "
b11111111 $
b11111111 #
#768
b110000000 !
b110000000 %
b100000000 "
b100000000 $
b100000000 #
#771
b110000001 !
b110000001 %
b100000001 "
b100000001 $
b100000001 #
#774
b110000011 !
b110000011 %
b100000010 "
b100000010 $
b100000010 #
#777
b110000010 !
b110000010 %
b100000011 "
b100000011 $
b100000011 #
#780
b110000110 !
b110000110 %
b100000100 "
b100000100 $
b100000100 #
#783
b110000111 !
b110000111 %
b100000101 "
b100000101 $
b100000101 #
#786
b110000101 !
b110000101 %
b100000110 "
b100000110 $
b100000110 #
#789
b110000100 !
b110000100 %
b100000111 "
b100000111 $
b100000111 #
#792
b110001100 !
b110001100 %
b100001000 "
b100001000 $
b100001000 #
#795
b110001101 !
b110001101 %
b100001001 "
b100001001 $
b100001001 #
#798
b110001111 !
b110001111 %
b100001010 "
b100001010 $
b100001010 #
#801
b110001110 !
b110001110 %
b100001011 "
b100001011 $
b100001011 #
#804
b110001010 !
b110001010 %
b100001100 "
b100001100 $
b100001100 #
#807
b110001011 !
b110001011 %
b100001101 "
b100001101 $
b100001101 #
#810
b110001001 !
b110001001 %
b100001110 "
b100001110 $
b100001110 #
#813
b110001000 !
b110001000 %
b100001111 "
b100001111 $
b100001111 #
#816
b110011000 !
b110011000 %
b100010000 "
b100010000 $
b100010000 #
#819
b110011001 !
b110011001 %
b100010001 "
b100010001 $
b100010001 #
#822
b110011011 !
b110011011 %
b100010010 "
b100010010 $
b100010010 #
#825
b110011010 !
b110011010 %
b100010011 "
b100010011 $
b100010011 #
#828
b110011110 !
b110011110 %
b100010100 "
b100010100 $
b100010100 #
#831
b110011111 !
b110011111 %
b100010101 "
b100010101 $
b100010101 #
#834
b110011101 !
b110011101 %
b100010110 "
b100010110 $
b100010110 #
#837
b110011100 !
b110011100 %
b100010111 "
b100010111 $
b100010111 #
#840
b110010100 !
b110010100 %
b100011000 "
b100011000 $
b100011000 #
#843
b110010101 !
b110010101 %
b100011001 "
b100011001 $
b100011001 #
#846
b110010111 !
b110010111 %
b100011010 "
b100011010 $
b100011010 #
#849
b110010110 !
b110010110 %
b100011011 "
b100011011 $
b100011011 #
#852
b110010010 !
b110010010 %
b100011100 "
b100011100 $
b100011100 #
#855
b110010011 !
b110010011 %
b100011101 "
b100011101 $
b100011101 #
#858
b110010001 !
b110010001 %
b100011110 "
b100011110 $
b100011110 #
#861
b110010000 !
b110010000 %
b100011111 "
b100011111 $
b100011111 #
#864
b110110000 !
b110110000 %
b100100000 "
b100100000 $
b100100000 #
#867
b110110001 !
b110110001 %
b100100001 "
b100100001 $
b100100001 #
#870
b110110011 !
b110110011 %
b100100010 "
b100100010 $
b100100010 #
#873
b110110010 !
b110110010 %
b100100011 "
b100100011 $
b100100011 #
#876
b110110110 !
b110110110 %
b100100100 "
b100100100 $
b100100100 #
#879
b110110111 !
b110110111 %
b100100101 "
b100100101 $
b100100101 #
#882
b110110101 !
b110110101 %
b100100110 "
b100100110 $
b100100110 #
#885
b110110100 !
b110110100 %
b100100111 "
b100100111 $
b100100111 #
#888
b110111100 !
b110111100 %
b100101000 "
b100101000 $
b100101000 #
#891
b110111101 !
b110111101 %
b100101001 "
b100101001 $
b100101001 #
#894
b110111111 !
b110111111 %
b100101010 "
b100101010 $
b100101010 #
#897
b110111110 !
b110111110 %
b100101011 "
b100101011 $
b100101011 #
#900
b110111010 !
b110111010 %
b100101100 "
b100101100 $
b100101100 #
#903
b110111011 !
b110111011 %
b100101101 "
b100101101 $
b100101101 #
#906
b110111001 !
b110111001 %
b100101110 "
b100101110 $
b100101110 #
#909
b110111000 !
b110111000 %
b100101111 "
b100101111 $
b100101111 #
#912
b110101000 !
b110101000 %
b100110000 "
b100110000 $
b100110000 #
#915
b110101001 !
b110101001 %
b100110001 "
b100110001 $
b100110001 #
#918
b110101011 !
b110101011 %
b100110010 "
b100110010 $
b100110010 #
#921
b110101010 !
b110101010 %
b100110011 "
b100110011 $
b100110011 #
#924
b110101110 !
b110101110 %
b100110100 "
b100110100 $
b100110100 #
#927
b110101111 !
b110101111 %
b100110101 "
b100110101 $
b100110101 #
#930
b110101101 !
b110101101 %
b100110110 "
b100110110 $
b100110110 #
#933
b110101100 !
b110101100 %
b100110111 "
b100110111 $
b100110111 #
#936
b110100100 !
b110100100 %
b100111000 "
b100111000 $
b100111000 #
#939
b110100101 !
b110100101 %
b100111001 "
b100111001 $
b100111001 #
#942
b110100111 !
b110100111 %
b100111010 "
b100111010 $
b100111010 #
#945
b110100110 !
b110100110 %
b100111011 "
b100111011 $
b100111011 #
#948
b110100010 !
b110100010 %
b100111100 "
b100111100 $
b100111100 #
#951
b110100011 !
b110100011 %
b100111101 "
b100111101 $
b100111101 #
#954
b110100001 !
b110100001 %
b100111110 "
b100111110 $
b100111110 #
#957
b110100000 !
b110100000 %
b100111111 "
b100111111 $
b100111111 #
#960
b111100000 !
b111100000 %
b101000000 "
b101000000 $
b101000000 #
#963
b111100001 !
b111100001 %
b101000001 "
b101000001 $
b101000001 #
#966
b111100011 !
b111100011 %
b101000010 "
b101000010 $
b101000010 #
#969
b111100010 !
b111100010 %
b101000011 "
b101000011 $
b101000011 #
#972
b111100110 !
b111100110 %
b101000100 "
b101000100 $
b101000100 #
#975
b111100111 !
b111100111 %
b101000101 "
b101000101 $
b101000101 #
#978
b111100101 !
b111100101 %
b101000110 "
b101000110 $
b101000110 #
#981
b111100100 !
b111100100 %
b101000111 "
b101000111 $
b101000111 #
#984
b111101100 !
b111101100 %
b101001000 "
b101001000 $
b101001000 #
#987
b111101101 !
b111101101 %
b101001001 "
b101001001 $
b101001001 #
#990
b111101111 !
b111101111 %
b101001010 "
b101001010 $
b101001010 #
#993
b111101110 !
b111101110 %
b101001011 "
b101001011 $
b101001011 #
#996
b111101010 !
b111101010 %
b101001100 "
b101001100 $
b101001100 #
#999
b111101011 !
b111101011 %
b101001101 "
b101001101 $
b101001101 #
#1002
b111101001 !
b111101001 %
b101001110 "
b101001110 $
b101001110 #
#1005
b111101000 !
b111101000 %
b101001111 "
b101001111 $
b101001111 #
#1008
b111111000 !
b111111000 %
b101010000 "
b101010000 $
b101010000 #
#1011
b111111001 !
b111111001 %
b101010001 "
b101010001 $
b101010001 #
#1014
b111111011 !
b111111011 %
b101010010 "
b101010010 $
b101010010 #
#1017
b111111010 !
b111111010 %
b101010011 "
b101010011 $
b101010011 #
#1020
b111111110 !
b111111110 %
b101010100 "
b101010100 $
b101010100 #
#1023
b111111111 !
b111111111 %
b101010101 "
b101010101 $
b101010101 #
#1026
b111111101 !
b111111101 %
b101010110 "
b101010110 $
b101010110 #
#1029
b111111100 !
b111111100 %
b101010111 "
b101010111 $
b101010111 #
#1032
b111110100 !
b111110100 %
b101011000 "
b101011000 $
b101011000 #
#1035
b111110101 !
b111110101 %
b101011001 "
b101011001 $
b101011001 #
#1038
b111110111 !
b111110111 %
b101011010 "
b101011010 $
b101011010 #
#1041
b111110110 !
b111110110 %
b101011011 "
b101011011 $
b101011011 #
#1044
b111110010 !
b111110010 %
b101011100 "
b101011100 $
b101011100 #
#1047
b111110011 !
b111110011 %
b101011101 "
b101011101 $
b101011101 #
#1050
b111110001 !
b111110001 %
b101011110 "
b101011110 $
b101011110 #
#1053
b111110000 !
b111110000 %
b101011111 "
b101011111 $
b101011111 #
#1056
b111010000 !
b111010000 %
b101100000 "
b101100000 $
b101100000 #
#1059
b111010001 !
b111010001 %
b101100001 "
b101100001 $
b101100001 #
#1062
b111010011 !
b111010011 %
b101100010 "
b101100010 $
b101100010 #
#1065
b111010010 !
b111010010 %
b101100011 "
b101100011 $
b101100011 #
#1068
b111010110 !
b111010110 %
b101100100 "
b101100100 $
b101100100 #
#1071
b111010111 !
b111010111 %
b101100101 "
b101100101 $
b101100101 #
#1074
b111010101 !
b111010101 %
b101100110 "
b101100110 $
b101100110 #
#1077
b111010100 !
b111010100 %
b101100111 "
b101100111 $
b101100111 #
#1080
b111011100 !
b111011100 %
b101101000 "
b101101000 $
b101101000 #
#1083
b111011101 !
b111011101 %
b101101001 "
b101101001 $
b101101001 #
#1086
b111011111 !
b111011111 %
b101101010 "
b101101010 $
b101101010 #
#1089
b111011110 !
b111011110 %
b101101011 "
b101101011 $
b101101011 #
#1092
b111011010 !
b111011010 %
b101101100 "
b101101100 $
b101101100 #
#1095
b111011011 !
b111011011 %
b101101101 "
b101101101 $
b101101101 #
#1098
b111011001 !
b111011001 %
b101101110 "
b101101110 $
b101101110 #
#1101
b111011000 !
b111011000 %
b101101111 "
b101101111 $
b101101111 #
#1104
b111001000 !
b111001000 %
b101110000 "
b101110000 $
b101110000 #
#1107
b111001001 !
b111001001 %
b101110001 "
b101110001 $
b101110001 #
#1110
b111001011 !
b111001011 %
b101110010 "
b101110010 $
b101110010 #
#1113
b111001010 !
b111001010 %
b101110011 "
b101110011 $
b101110011 #
#1116
b111001110 !
b111001110 %
b101110100 "
b101110100 $
b101110100 #
#1119
b111001111 !
b111001111 %
b101110101 "
b101110101 $
b101110101 #
#1122
b111001101 !
b111001101 %
b101110110 "
b101110110 $
b101110110 #
#1125
b111001100 !
b111001100 %
b101110111 "
b101110111 $
b101110111 #
