combinational/full_sub/full_sub_struct.v
module full_sub_struct(
        input a,b,c_in ,
        output diff , borrow );

        wire x,y,z,p,q; 
        xor g1 (x,a,b);
        xor g2(diff,x,c_in);
        not g3(y,a);
        and g4(z,y,b);
        not g5(p,x);
        and g6(q,p,c_in);
        or g7(borrow,z,q);

endmodule

2_combinational/full_sub/full_sub_tb.v
module full_sub_tb;

    reg a, b, c_in;
    wire diff, borrow;

    full_sub_struct uut (
        .a(a),
        .b(b),
        .c_in(c_in),
        .diff(diff),
        .borrow(borrow)
    );

    initial begin

        {a,b,c_in}=3'b000; #10;
        $display("%b %b %b | %b %b",a,b,c_in,diff,borrow);

        {a,b,c_in}=3'b001; #10;
        $display("%b %b %b | %b %b",a,b,c_in,diff,borrow);

        {a,b,c_in}=3'b010; #10;
        $display("%b %b %b | %b %b",a,b,c_in,diff,borrow);

        {a,b,c_in}=3'b011; #10;
        $display("%b %b %b | %b %b",a,b,c_in,diff,borrow);

        {a,b,c_in}=3'b100; #10;
        $display("%b %b %b | %b %b",a,b,c_in,diff,borrow);

        {a,b,c_in}=3'b101; #10;
        $display("%b %b %b | %b %b",a,b,c_in,diff,borrow);

        {a,b,c_in}=3'b110; #10;
        $display("%b %b %b | %b %b",a,b,c_in,diff,borrow);

        {a,b,c_in}=3'b111; #10;
        $display("%b %b %b | %b %b",a,b,c_in,diff,borrow);

        $finish;

    end

    initial begin
        $dumpfile("full_sub.vcd");
        $dumpvars(0,full_sub_tb);
    end

endmodule

2_combinational/full_sub/full_sub.vcd
$date
	Thu Jun  4 18:17:31 2026
$end
$version
	Icarus Verilog
$end
$timescale
	1s
$end
$scope module full_sub_tb $end
$var wire 1 ! diff $end
$var wire 1 " borrow $end
$var reg 1 # a $end
$var reg 1 $ b $end
$var reg 1 % c_in $end
$scope module uut $end
$var wire 1 # a $end
$var wire 1 $ b $end
$var wire 1 " borrow $end
$var wire 1 % c_in $end
$var wire 1 ! diff $end
$var wire 1 & p $end
$var wire 1 ' q $end
$var wire 1 ( x $end
$var wire 1 ) y $end
$var wire 1 * z $end
$upscope $end
$upscope $end
$enddefinitions $end
$comment Show the parameter values. $end
$dumpall
$end
#0
$dumpvars
0*
1)
0(
0'
1&
0%
0$
0#
0"
0!
$end
#10
1"
1!
1'
1%
#20
0&
1(
1*
1!
0'
1$
0%
#30
0!
1%
#40
0"
0)
0*
1!
1#
0$
0%
#50
0!
1%
#60
1&
0(
0!
1$
0%
#70
1"
1!
1'
1%
