extra/sin_lut.v
`timescale 1ns/1ps

module sin_lut (
    input        clk,
    input        rst,
    output reg [7:0] sine_out
);

reg [3:0] addr;

always @(posedge clk or posedge rst) begin
    if (rst)
        addr <= 4'd0;
    else
        addr <= addr + 1'b1;
end

always @(*) begin
    case (addr)
        4'd0  : sine_out = 8'd128;
        4'd1  : sine_out = 8'd177;
        4'd2  : sine_out = 8'd218;
        4'd3  : sine_out = 8'd245;
        4'd4  : sine_out = 8'd255;
        4'd5  : sine_out = 8'd245;
        4'd6  : sine_out = 8'd218;
        4'd7  : sine_out = 8'd177;
        4'd8  : sine_out = 8'd128;
        4'd9  : sine_out = 8'd79;
        4'd10 : sine_out = 8'd38;
        4'd11 : sine_out = 8'd11;
        4'd12 : sine_out = 8'd0;
        4'd13 : sine_out = 8'd11;
        4'd14 : sine_out = 8'd38;
        4'd15 : sine_out = 8'd79;
        default: sine_out = 8'd128;
    endcase
end

endmodule

extra/sin_lut_tb.v
module tb_sine_lut;

reg clk;
reg rst;
wire [7:0] sine_out;

sin_lut dut (
    .clk(clk),
    .rst(rst),
    .sine_out(sine_out)
);

always #5 clk = ~clk;

initial begin
    clk = 0;
    rst = 1;

    #12 rst = 0;

    #200 $finish;
end

initial begin
    $display("Time\tSine_Out");
    $monitor("%0t\t%d", $time, sine_out);
end

initial begin
    $dumpfile("sine_lut.vcd");
    $dumpvars(0, tb_sine_lut);
end

endmodule

extra/sine_lut.vcd
$date
	Tue Jun 16 12:57:12 2026
$end
$version
	Icarus Verilog
$end
$timescale
	1ps
$end
$scope module tb_sine_lut $end
$var wire 8 ! sine_out [7:0] $end
$var reg 1 " clk $end
$var reg 1 # rst $end
$scope module dut $end
$var wire 1 " clk $end
$var wire 1 # rst $end
$var reg 4 $ addr [3:0] $end
$var reg 8 % sine_out [7:0] $end
$upscope $end
$upscope $end
$enddefinitions $end
$comment Show the parameter values. $end
$dumpall
$end
#0
$dumpvars
b10000000 %
b0 $
1#
0"
b10000000 !
$end
#5000
1"
#10000
0"
#12000
0#
#15000
b10110001 !
b10110001 %
b1 $
1"
#20000
0"
#25000
b11011010 !
b11011010 %
b10 $
1"
#30000
0"
#35000
b11110101 !
b11110101 %
b11 $
1"
#40000
0"
#45000
b11111111 !
b11111111 %
b100 $
1"
#50000
0"
#55000
b11110101 !
b11110101 %
b101 $
1"
#60000
0"
#65000
b11011010 !
b11011010 %
b110 $
1"
#70000
0"
#75000
b10110001 !
b10110001 %
b111 $
1"
#80000
0"
#85000
b10000000 !
b10000000 %
b1000 $
1"
#90000
0"
#95000
b1001111 !
b1001111 %
b1001 $
1"
#100000
0"
#105000
b100110 !
b100110 %
b1010 $
1"
#110000
0"
#115000
b1011 !
b1011 %
b1011 $
1"
#120000
0"
#125000
b0 !
b0 %
b1100 $
1"
#130000
0"
#135000
b1011 !
b1011 %
b1101 $
1"
#140000
0"
#145000
b100110 !
b100110 %
b1110 $
1"
#150000
0"
#155000
b1001111 !
b1001111 %
b1111 $
1"
#160000
0"
#165000
b10000000 !
b10000000 %
b0 $
1"
#170000
0"
#175000
b10110001 !
b10110001 %
b1 $
1"
#180000
0"
#185000
b11011010 !
b11011010 %
b10 $
1"
#190000
0"
#195000
b11110101 !
b11110101 %
b11 $
1"
#200000
0"
#205000
b11111111 !
b11111111 %
b100 $
1"
