2_combinational/full_add/full_adder_struct.v
module full_adder_struct(
	input a,b,c_in ,
	output s,c_out
 );

	wire w,x,y,z ;

	xor g1(w,a,b);
	xor g2(s,w,c_in);
	and g3(x,a,b);
	and g4(y,b,c_in);
	and g5(z,a,c_in);
	or g6(c_out,x,y,z);

endmodule

2_combinational/full_add/full_adder_tb.v
module full_adder_tb;
    reg a, b, c_in;
    wire s, c_out;

    full_adder_struct uut (
        .a(a),
        .b(b),
        .c_in(c_in),
        .s(s),
        .c_out(c_out)
    );

    initial begin
        {a, b, c_in} = 3'b000; #10;
        $display("%b %b  %b    | %b  %b", a, b, c_in, s, c_out);

        {a, b, c_in} = 3'b001; #10;
        $display("%b %b  %b    | %b  %b", a, b, c_in, s, c_out);

        {a, b, c_in} = 3'b010; #10;
        $display("%b %b  %b    | %b  %b", a, b, c_in, s, c_out);

        {a, b, c_in} = 3'b011; #10;
        $display("%b %b  %b    | %b  %b", a, b, c_in, s, c_out);

        {a, b, c_in} = 3'b100; #10;
        $display("%b %b  %b    | %b  %b", a, b, c_in, s, c_out);

        {a, b, c_in} = 3'b101; #10;
        $display("%b %b  %b    | %b  %b", a, b, c_in, s, c_out);

        {a, b, c_in} = 3'b110; #10;
        $display("%b %b  %b    | %b  %b", a, b, c_in, s, c_out);

        {a, b, c_in} = 3'b111; #10;
        $display("%b %b  %b    | %b  %b", a, b, c_in, s, c_out);

        $finish;
    end

    
    initial begin
        $dumpfile("full_adder.vcd");
        $dumpvars(0, full_adder_tb);
    end

endmodule

2_combinational/full_add/full_adder.vcd
$date
	Wed Jun  3 05:51:59 2026
$end
$version
	Icarus Verilog
$end
$timescale
	1s
$end
$scope module full_adder_tb $end
$var wire 1 ! s $end
$var wire 1 " c_out $end
$var reg 1 # a $end
$var reg 1 $ b $end
$var reg 1 % c_in $end
$scope module uut $end
$var wire 1 # a $end
$var wire 1 $ b $end
$var wire 1 % c_in $end
$var wire 1 " c_out $end
$var wire 1 ! s $end
$var wire 1 & w $end
$var wire 1 ' x $end
$var wire 1 ( y $end
$var wire 1 ) z $end
$upscope $end
$upscope $end
$enddefinitions $end
$comment Show the parameter values. $end
$dumpall
$end
#0
$dumpvars
0)
0(
0'
0&
0%
0$
0#
0"
0!
$end
#10
1!
1%
#20
1&
1!
1$
0%
#30
1"
0!
1(
1%
#40
0"
1!
0(
1#
0$
0%
#50
1"
0!
1)
1%
#60
0&
1'
0!
0)
1$
0%
#70
1!
1(
1)
1%
