3_Intermediate_Combinational/Priority_Encoder/Priority_encoder_data_always_case.v
module Priority_encoder_data_always_case(input [3:0]a,output reg [1:0]y);
always @(*) begin
casez(a)
        4'b1???: y = 2'b11;
        4'b01??: y = 2'b10;
        4'b001?: y = 2'b01;
        4'b0001: y = 2'b00;
        default: y = 2'b00;
    endcase
end 
endmodule

3_Intermediate_Combinational/Priority_Encoder/Priority_encoder_tb.v
module Priority_encoder_tb;
reg [3:0]a;
wire [1:0]y;

integer i;

Priority_encoder_data_always_case uut(.a(a),.y(y));
initial begin
$dumpfile("Priority_encoder.vcd");
$dumpvars(0,Priority_encoder_tb);

$monitor("time=%0t,a=%b%b%b%b,y=%b%b",$time,a[3],a[2],a[1],a[0],y[1],y[0]);
for(i=0;i<16;i=i+1)
begin
a=i;
#10;
end
$finish;
end
endmodule

3_Intermediate_Combinational/Priority_Encoder/Priority_encoder.vcd
$date
	Tue Jun  9 06:28:35 2026
$end
$version
	Icarus Verilog
$end
$timescale
	1s
$end
$scope module Priority_encoder_tb $end
$var wire 2 ! y [1:0] $end
$var reg 4 " a [3:0] $end
$var integer 32 # i [31:0] $end
$scope module uut $end
$var wire 4 $ a [3:0] $end
$var reg 2 % y [1:0] $end
$upscope $end
$upscope $end
$enddefinitions $end
$comment Show the parameter values. $end
$dumpall
$end
#0
$dumpvars
b0 %
b0 $
b0 #
b0 "
b0 !
$end
#10
b1 "
b1 $
b1 #
#20
b1 !
b1 %
b10 "
b10 $
b10 #
#30
b11 "
b11 $
b11 #
#40
b10 !
b10 %
b100 "
b100 $
b100 #
#50
b101 "
b101 $
b101 #
#60
b110 "
b110 $
b110 #
#70
b111 "
b111 $
b111 #
#80
b11 !
b11 %
b1000 "
b1000 $
b1000 #
#90
b1001 "
b1001 $
b1001 #
#100
b1010 "
b1010 $
b1010 #
#110
b1011 "
b1011 $
b1011 #
#120
b1100 "
b1100 $
b1100 #
#130
b1101 "
b1101 $
b1101 #
#140
b1110 "
b1110 $
b1110 #
#150
b1111 "
b1111 $
b1111 #
#160
b10000 #
