2_combinational/decoder_3x8/decoder_3x8_struct.v
module decoder_3x8_struct(
    input A,
    input B,
    input C,
    output Y0,
    output Y1,
    output Y2,
    output Y3,
    output Y4,
    output Y5,
    output Y6,
    output Y7
);

wire A_bar, B_bar, C_bar;

not g1(A_bar,A);
not g2(B_bar,B);
not g3(C_bar,C);

and g4(Y0,A_bar,B_bar,C_bar);
and g5(Y1,A_bar,B_bar,C);
and g6(Y2,A_bar,B,C_bar);
and g7(Y3,A_bar,B,C);

and g8(Y4,A,B_bar,C_bar);
and g9(Y5,A,B_bar,C);
and g10(Y6,A,B,C_bar);
and g11(Y7,A,B,C);

endmodule

2_combinational/decoder_3x8/decoder_3x8_tb.v
module decoder_3x8_tb;
reg A,B,C;
wire Y0,Y1,Y2,Y3,Y4,Y5,Y6,Y7;
decoder_3x8_struct uut(
.A(A),
.B(B),
.C(C),
.Y0(Y0),
.Y1(Y1),
.Y2(Y2),
.Y3(Y3),
.Y4(Y4),
.Y5(Y5),
.Y6(Y6),
.Y7(Y7)
);
initial begin
	$dumpfile("decoder_3x8.vcd");
	$dumpvars(0,decoder_3x8_tb);

	$display("A B C | Y0 Y1 Y2 Y3 Y4 Y5 Y6 Y7");
	{A,B,C}=3'b000;
	#10;
	$display("%b %b %b | %b %b %b %b %b %b %b %b",A,B,C,Y0,Y1,Y2,Y3,Y4,Y5,Y6,Y7);
	{A,B,C}=3'b001;
	#10;
	$display("%b %b %b | %b %b %b %b %b %b %b %b",A,B,C,Y0,Y1,Y2,Y3,Y4,Y5,Y6,Y7);
	{A,B,C}=3'b010;
	#10;
	$display("%b %b %b | %b %b %b %b %b %b %b %b",A,B,C,Y0,Y1,Y2,Y3,Y4,Y5,Y6,Y7);
	{A,B,C}=3'b011;
	#10;
	$display("%b %b %b | %b %b %b %b %b %b %b %b",A,B,C,Y0,Y1,Y2,Y3,Y4,Y5,Y6,Y7);
	{A,B,C}=3'b100;
	#10;
	$display("%b %b %b | %b %b %b %b %b %b %b %b",A,B,C,Y0,Y1,Y2,Y3,Y4,Y5,Y6,Y7);
	{A,B,C}=3'b101;
	#10;
	$display("%b %b %b | %b %b %b %b %b %b %b %b",A,B,C,Y0,Y1,Y2,Y3,Y4,Y5,Y6,Y7);
	{A,B,C}=3'b110;
	#10;
	$display("%b %b %b | %b %b %b %b %b %b %b %b",A,B,C,Y0,Y1,Y2,Y3,Y4,Y5,Y6,Y7);
	{A,B,C}=3'b111;
	#10;
	$display("%b %b %b | %b %b %b %b %b %b %b %b",A,B,C,Y0,Y1,Y2,Y3,Y4,Y5,Y6,Y7);
$finish;
end
endmodule

combinational/decoder_3x8/decoder_3x8.vcd
$date
	Sun Jun  7 18:00:12 2026
$end
$version
	Icarus Verilog
$end
$timescale
	1s
$end
$scope module decoder_3x8_tb $end
$var wire 1 ! Y7 $end
$var wire 1 " Y6 $end
$var wire 1 # Y5 $end
$var wire 1 $ Y4 $end
$var wire 1 % Y3 $end
$var wire 1 & Y2 $end
$var wire 1 ' Y1 $end
$var wire 1 ( Y0 $end
$var reg 1 ) A $end
$var reg 1 * B $end
$var reg 1 + C $end
$scope module uut $end
$var wire 1 ) A $end
$var wire 1 , A_bar $end
$var wire 1 * B $end
$var wire 1 - B_bar $end
$var wire 1 + C $end
$var wire 1 . C_bar $end
$var wire 1 ( Y0 $end
$var wire 1 ' Y1 $end
$var wire 1 & Y2 $end
$var wire 1 % Y3 $end
$var wire 1 $ Y4 $end
$var wire 1 # Y5 $end
$var wire 1 " Y6 $end
$var wire 1 ! Y7 $end
$upscope $end
$upscope $end
$enddefinitions $end
$comment Show the parameter values. $end
$dumpall
$end
#0
$dumpvars
1.
1-
1,
0+
0*
0)
1(
0'
0&
0%
0$
0#
0"
0!
$end
#10
0(
0.
1'
1+
#20
0-
1&
1.
0'
1*
0+
#30
0&
0.
1%
1+
#40
0,
1$
1-
1.
0%
1)
0*
0+
#50
0$
0.
1#
1+
#60
0-
1"
1.
0#
1*
0+
#70
0"
0.
1!
1+
