3_Intermediate_Combinational/Ripple_Carry_Adder/ripple_carry_adder_data.v
module ripple_carry_adder_data(input [3:0]a,input [3:0]b,input cin,output c,output [3:0]s);
wire w1,w2,w3;

assign s[0] = a[0]^b[0]^cin;
assign w1= (a[0]&b[0] | (a[0]^b[0])&cin);

assign s[1] = a[1]^b[1]^w1;
assign w2= (a[1]&b[1] | (a[1]^b[1])&w1);

assign s[2] = a[2]^b[2]^w2;
assign w3=( a[2]&b[2] | (a[2]^b[2])&w2);

assign s[3] = a[3]^b[3]^w3;
assign c=(a[3]&b[3] | (a[3]^b[3])&w3);

endmodule

3_Intermediate_Combinational/Ripple_Carry_Adder/ripple_carry_adder_tb.v
module ripple_carry_adder_tb;

reg [3:0]a,b;
reg cin;
wire [3:0]s;
wire c;

ripple_carry_adder_data uut(.a(a),.b(b),.cin(cin),.c(c),.s(s));

integer i;

initial
begin
$dumpfile("ripple_carry_adder.vcd");
$dumpvars(0,ripple_carry_adder_tb);

$monitor("t=%0t,a=%b,b=%b,cin=%b,s=%b,cout=%b",$time,a,b,cin,s,c);

for(i=0;i<256;i=i+1)begin
{a,b,cin}=i;
#10;
end

end

endmodule

3_Intermediate_Combinational/Ripple_Carry_Adder/ripple_carry_adder.vcd
$date
	Mon Jun 15 06:50:53 2026
$end
$version
	Icarus Verilog
$end
$timescale
	1s
$end
$scope module ripple_carry_adder_tb $end
$var wire 4 ! s [3:0] $end
$var wire 1 " c $end
$var reg 4 # a [3:0] $end
$var reg 4 $ b [3:0] $end
$var reg 1 % cin $end
$var integer 32 & i [31:0] $end
$scope module uut $end
$var wire 4 ' a [3:0] $end
$var wire 4 ( b [3:0] $end
$var wire 1 " c $end
$var wire 1 % cin $end
$var wire 1 ) w1 $end
$var wire 1 * w2 $end
$var wire 1 + w3 $end
$var wire 4 , s [3:0] $end
$upscope $end
$upscope $end
$enddefinitions $end
$comment Show the parameter values. $end
$dumpall
$end
#0
$dumpvars
b0 ,
0+
0*
0)
b0 (
b0 '
b0 &
0%
b0 $
b0 #
0"
b0 !
$end
#10
b1 !
b1 ,
1%
b1 &
#20
b1 !
b1 ,
b1 $
b1 (
0%
b10 &
#30
1)
b10 !
b10 ,
1%
b11 &
#40
0)
b10 !
b10 ,
b10 $
b10 (
0%
b100 &
#50
b11 !
b11 ,
1%
b101 &
#60
b11 !
b11 ,
b11 $
b11 (
0%
b110 &
#70
1*
1)
b100 !
b100 ,
1%
b111 &
#80
0+
0*
0)
b100 !
b100 ,
b100 $
b100 (
0%
b1000 &
#90
b101 !
b101 ,
1%
b1001 &
#100
b101 !
b101 ,
b101 $
b101 (
0%
b1010 &
#110
1)
b110 !
b110 ,
1%
b1011 &
#120
0)
b110 !
b110 ,
b110 $
b110 (
0%
b1100 &
#130
b111 !
b111 ,
1%
b1101 &
#140
b111 !
b111 ,
b111 $
b111 (
0%
b1110 &
#150
1+
1*
1)
b1000 !
b1000 ,
1%
b1111 &
#160
0+
0"
0*
0)
b1000 !
b1000 ,
b1000 $
b1000 (
0%
b10000 &
#170
b1001 !
b1001 ,
1%
b10001 &
#180
b1001 !
b1001 ,
b1001 $
b1001 (
0%
b10010 &
#190
1)
b1010 !
b1010 ,
1%
b10011 &
#200
0)
b1010 !
b1010 ,
b1010 $
b1010 (
0%
b10100 &
#210
b1011 !
b1011 ,
1%
b10101 &
#220
b1011 !
b1011 ,
b1011 $
b1011 (
0%
b10110 &
#230
1*
1)
b1100 !
b1100 ,
1%
b10111 &
#240
0"
0+
0*
0)
b1100 !
b1100 ,
b1100 $
b1100 (
0%
b11000 &
#250
b1101 !
b1101 ,
1%
b11001 &
#260
b1101 !
b1101 ,
b1101 $
b1101 (
0%
b11010 &
#270
1)
b1110 !
b1110 ,
1%
b11011 &
#280
0)
b1110 !
b1110 ,
b1110 $
b1110 (
0%
b11100 &
#290
b1111 !
b1111 ,
1%
b11101 &
#300
b1111 !
b1111 ,
b1111 $
b1111 (
0%
b11110 &
#310
1"
1+
1*
1)
b0 !
b0 ,
1%
b11111 &
#320
0+
0"
0*
0)
b1 !
b1 ,
b1 #
b1 '
b0 $
b0 (
0%
b100000 &
#330
1)
b10 !
b10 ,
1%
b100001 &
#340
1)
b10 !
b10 ,
b1 $
b1 (
0%
b100010 &
#350
b11 !
b11 ,
1%
b100011 &
#360
0*
0)
b11 !
b11 ,
b10 $
b10 (
0%
b100100 &
#370
1*
1)
b100 !
b100 ,
1%
b100101 &
#380
1*
1)
b100 !
b100 ,
b11 $
b11 (
0%
b100110 &
#390
b101 !
b101 ,
1%
b100111 &
#400
0*
0+
0)
b101 !
b101 ,
b100 $
b100 (
0%
b101000 &
#410
1)
b110 !
b110 ,
1%
b101001 &
#420
1)
b110 !
b110 ,
b101 $
b101 (
0%
b101010 &
#430
b111 !
b111 ,
1%
b101011 &
#440
0+
0*
0)
b111 !
b111 ,
b110 $
b110 (
0%
b101100 &
#450
1+
1*
1)
b1000 !
b1000 ,
1%
b101101 &
#460
1+
1*
1)
b1000 !
b1000 ,
b111 $
b111 (
0%
b101110 &
#470
b1001 !
b1001 ,
1%
b101111 &
#480
0*
0+
0"
0)
b1001 !
b1001 ,
b1000 $
b1000 (
0%
b110000 &
#490
1)
b1010 !
b1010 ,
1%
b110001 &
#500
1)
b1010 !
b1010 ,
b1001 $
b1001 (
0%
b110010 &
#510
b1011 !
b1011 ,
1%
b110011 &
#520
0*
0)
b1011 !
b1011 ,
b1010 $
b1010 (
0%
b110100 &
#530
1*
1)
b1100 !
b1100 ,
1%
b110101 &
#540
1*
1)
b1100 !
b1100 ,
b1011 $
b1011 (
0%
b110110 &
#550
b1101 !
b1101 ,
1%
b110111 &
#560
0"
0*
0+
0)
b1101 !
b1101 ,
b1100 $
b1100 (
0%
b111000 &
#570
1)
b1110 !
b1110 ,
1%
b111001 &
#580
1)
b1110 !
b1110 ,
b1101 $
b1101 (
0%
b111010 &
#590
b1111 !
b1111 ,
1%
b111011 &
#600
0"
0+
0*
0)
b1111 !
b1111 ,
b1110 $
b1110 (
0%
b111100 &
#610
1"
1+
1*
1)
b0 !
b0 ,
1%
b111101 &
#620
1"
1+
1*
1)
b0 !
b0 ,
b1111 $
b1111 (
0%
b111110 &
#630
b1 !
b1 ,
1%
b111111 &
#640
0*
0+
0"
0)
b10 !
b10 ,
b10 #
b10 '
b0 $
b0 (
0%
b1000000 &
#650
b11 !
b11 ,
1%
b1000001 &
#660
b11 !
b11 ,
b1 $
b1 (
0%
b1000010 &
#670
1*
1)
b100 !
b100 ,
1%
b1000011 &
#680
0)
b100 !
b100 ,
b10 $
b10 (
0%
b1000100 &
#690
b101 !
b101 ,
1%
b1000101 &
#700
b101 !
b101 ,
b11 $
b11 (
0%
b1000110 &
#710
1)
b110 !
b110 ,
1%
b1000111 &
#720
0+
0*
0)
b110 !
b110 ,
b100 $
b100 (
0%
b1001000 &
#730
b111 !
b111 ,
1%
b1001001 &
#740
b111 !
b111 ,
b101 $
b101 (
0%
b1001010 &
#750
1+
1*
1)
b1000 !
b1000 ,
1%
b1001011 &
#760
0)
b1000 !
b1000 ,
b110 $
b110 (
0%
b1001100 &
#770
b1001 !
b1001 ,
1%
b1001101 &
#780
b1001 !
b1001 ,
b111 $
b111 (
0%
b1001110 &
#790
1)
b1010 !
b1010 ,
1%
b1001111 &
#800
0+
0"
0*
0)
b1010 !
b1010 ,
b1000 $
b1000 (
0%
b1010000 &
#810
b1011 !
b1011 ,
1%
b1010001 &
#820
b1011 !
b1011 ,
b1001 $
b1001 (
0%
b1010010 &
#830
1*
1)
b1100 !
b1100 ,
1%
b1010011 &
#840
0)
b1100 !
b1100 ,
b1010 $
b1010 (
0%
b1010100 &
#850
b1101 !
b1101 ,
1%
b1010101 &
#860
b1101 !
b1101 ,
b1011 $
b1011 (
0%
b1010110 &
#870
1)
b1110 !
b1110 ,
1%
b1010111 &
#880
0"
0+
0*
0)
b1110 !
b1110 ,
b1100 $
b1100 (
0%
b1011000 &
#890
b1111 !
b1111 ,
1%
b1011001 &
#900
b1111 !
b1111 ,
b1101 $
b1101 (
0%
b1011010 &
#910
1"
1+
1*
1)
b0 !
b0 ,
1%
b1011011 &
#920
0)
b0 !
b0 ,
b1110 $
b1110 (
0%
b1011100 &
#930
b1 !
b1 ,
1%
b1011101 &
#940
b1 !
b1 ,
b1111 $
b1111 (
0%
b1011110 &
#950
1)
b10 !
b10 ,
1%
b1011111 &
#960
0+
0"
0*
0)
b11 !
b11 ,
b11 #
b11 '
b0 $
b0 (
0%
b1100000 &
#970
1*
1)
b100 !
b100 ,
1%
b1100001 &
#980
1*
1)
b100 !
b100 ,
b1 $
b1 (
0%
b1100010 &
#990
b101 !
b101 ,
1%
b1100011 &
#1000
0)
b101 !
b101 ,
b10 $
b10 (
0%
b1100100 &
#1010
1)
b110 !
b110 ,
1%
b1100101 &
#1020
1)
b110 !
b110 ,
b11 $
b11 (
0%
b1100110 &
#1030
b111 !
b111 ,
1%
b1100111 &
#1040
0*
0+
0)
b111 !
b111 ,
b100 $
b100 (
0%
b1101000 &
#1050
1+
1*
1)
b1000 !
b1000 ,
1%
b1101001 &
#1060
1+
1*
1)
b1000 !
b1000 ,
b101 $
b101 (
0%
b1101010 &
#1070
b1001 !
b1001 ,
1%
b1101011 &
#1080
0)
b1001 !
b1001 ,
b110 $
b110 (
0%
b1101100 &
#1090
1)
b1010 !
b1010 ,
1%
b1101101 &
#1100
1)
b1010 !
b1010 ,
b111 $
b111 (
0%
b1101110 &
#1110
b1011 !
b1011 ,
1%
b1101111 &
#1120
0*
0+
0"
0)
b1011 !
b1011 ,
b1000 $
b1000 (
0%
b1110000 &
#1130
1*
1)
b1100 !
b1100 ,
1%
b1110001 &
#1140
1*
1)
b1100 !
b1100 ,
b1001 $
b1001 (
0%
b1110010 &
#1150
b1101 !
b1101 ,
1%
b1110011 &
#1160
0)
b1101 !
b1101 ,
b1010 $
b1010 (
0%
b1110100 &
#1170
1)
b1110 !
b1110 ,
1%
b1110101 &
#1180
1)
b1110 !
b1110 ,
b1011 $
b1011 (
0%
b1110110 &
#1190
b1111 !
b1111 ,
1%
b1110111 &
#1200
0"
0*
0+
0)
b1111 !
b1111 ,
b1100 $
b1100 (
0%
b1111000 &
#1210
1"
1+
1*
1)
b0 !
b0 ,
1%
b1111001 &
#1220
1"
1+
1*
1)
b0 !
b0 ,
b1101 $
b1101 (
0%
b1111010 &
#1230
b1 !
b1 ,
1%
b1111011 &
#1240
0)
b1 !
b1 ,
b1110 $
b1110 (
0%
b1111100 &
#1250
1)
b10 !
b10 ,
1%
b1111101 &
#1260
1)
b10 !
b10 ,
b1111 $
b1111 (
0%
b1111110 &
#1270
b11 !
b11 ,
1%
b1111111 &
#1280
0+
0"
0)
0*
b100 !
b100 ,
b100 #
b100 '
b0 $
b0 (
0%
b10000000 &
#1290
b101 !
b101 ,
1%
b10000001 &
#1300
b101 !
b101 ,
b1 $
b1 (
0%
b10000010 &
#1310
1)
b110 !
b110 ,
1%
b10000011 &
#1320
0)
b110 !
b110 ,
b10 $
b10 (
0%
b10000100 &
#1330
b111 !
b111 ,
1%
b10000101 &
#1340
b111 !
b111 ,
b11 $
b11 (
0%
b10000110 &
#1350
1+
1*
1)
b1000 !
b1000 ,
1%
b10000111 &
#1360
0*
0)
b1000 !
b1000 ,
b100 $
b100 (
0%
b10001000 &
#1370
b1001 !
b1001 ,
1%
b10001001 &
#1380
b1001 !
b1001 ,
b101 $
b101 (
0%
b10001010 &
#1390
1)
b1010 !
b1010 ,
1%
b10001011 &
#1400
0)
b1010 !
b1010 ,
b110 $
b110 (
0%
b10001100 &
#1410
b1011 !
b1011 ,
1%
b10001101 &
#1420
b1011 !
b1011 ,
b111 $
b111 (
0%
b10001110 &
#1430
1*
1)
b1100 !
b1100 ,
1%
b10001111 &
#1440
0+
0"
0*
0)
b1100 !
b1100 ,
b1000 $
b1000 (
0%
b10010000 &
#1450
b1101 !
b1101 ,
1%
b10010001 &
#1460
b1101 !
b1101 ,
b1001 $
b1001 (
0%
b10010010 &
#1470
1)
b1110 !
b1110 ,
1%
b10010011 &
#1480
0)
b1110 !
b1110 ,
b1010 $
b1010 (
0%
b10010100 &
#1490
b1111 !
b1111 ,
1%
b10010101 &
#1500
b1111 !
b1111 ,
b1011 $
b1011 (
0%
b10010110 &
#1510
1"
1+
1*
1)
b0 !
b0 ,
1%
b10010111 &
#1520
0*
0)
b0 !
b0 ,
b1100 $
b1100 (
0%
b10011000 &
#1530
b1 !
b1 ,
1%
b10011001 &
#1540
b1 !
b1 ,
b1101 $
b1101 (
0%
b10011010 &
#1550
1)
b10 !
b10 ,
1%
b10011011 &
#1560
0)
b10 !
b10 ,
b1110 $
b1110 (
0%
b10011100 &
#1570
b11 !
b11 ,
1%
b10011101 &
#1580
b11 !
b11 ,
b1111 $
b1111 (
0%
b10011110 &
#1590
1*
1)
b100 !
b100 ,
1%
b10011111 &
#1600
0+
0"
0*
0)
b101 !
b101 ,
b101 #
b101 '
b0 $
b0 (
0%
b10100000 &
#1610
1)
b110 !
b110 ,
1%
b10100001 &
#1620
1)
b110 !
b110 ,
b1 $
b1 (
0%
b10100010 &
#1630
b111 !
b111 ,
1%
b10100011 &
#1640
0+
0*
0)
b111 !
b111 ,
b10 $
b10 (
0%
b10100100 &
#1650
1+
1*
1)
b1000 !
b1000 ,
1%
b10100101 &
#1660
1+
1*
1)
b1000 !
b1000 ,
b11 $
b11 (
0%
b10100110 &
#1670
b1001 !
b1001 ,
1%
b10100111 &
#1680
0*
0)
b1001 !
b1001 ,
b100 $
b100 (
0%
b10101000 &
#1690
1)
b1010 !
b1010 ,
1%
b10101001 &
#1700
1)
b1010 !
b1010 ,
b101 $
b101 (
0%
b10101010 &
#1710
b1011 !
b1011 ,
1%
b10101011 &
#1720
0*
0)
b1011 !
b1011 ,
b110 $
b110 (
0%
b10101100 &
#1730
1*
1)
b1100 !
b1100 ,
1%
b10101101 &
#1740
1*
1)
b1100 !
b1100 ,
b111 $
b111 (
0%
b10101110 &
#1750
b1101 !
b1101 ,
1%
b10101111 &
#1760
0+
0*
0"
0)
b1101 !
b1101 ,
b1000 $
b1000 (
0%
b10110000 &
#1770
1)
b1110 !
b1110 ,
1%
b10110001 &
#1780
1)
b1110 !
b1110 ,
b1001 $
b1001 (
0%
b10110010 &
#1790
b1111 !
b1111 ,
1%
b10110011 &
#1800
0"
0+
0*
0)
b1111 !
b1111 ,
b1010 $
b1010 (
0%
b10110100 &
#1810
1"
1+
1*
1)
b0 !
b0 ,
1%
b10110101 &
#1820
1"
1+
1*
1)
b0 !
b0 ,
b1011 $
b1011 (
0%
b10110110 &
#1830
b1 !
b1 ,
1%
b10110111 &
#1840
0*
0)
b1 !
b1 ,
b1100 $
b1100 (
0%
b10111000 &
#1850
1)
b10 !
b10 ,
1%
b10111001 &
#1860
1)
b10 !
b10 ,
b1101 $
b1101 (
0%
b10111010 &
#1870
b11 !
b11 ,
1%
b10111011 &
#1880
0*
0)
b11 !
b11 ,
b1110 $
b1110 (
0%
b10111100 &
#1890
1*
1)
b100 !
b100 ,
1%
b10111101 &
#1900
1*
1)
b100 !
b100 ,
b1111 $
b1111 (
0%
b10111110 &
#1910
b101 !
b101 ,
1%
b10111111 &
#1920
0+
0*
0"
0)
b110 !
b110 ,
b110 #
b110 '
b0 $
b0 (
0%
b11000000 &
#1930
b111 !
b111 ,
1%
b11000001 &
#1940
b111 !
b111 ,
b1 $
b1 (
0%
b11000010 &
#1950
1+
1*
1)
b1000 !
b1000 ,
1%
b11000011 &
#1960
0)
b1000 !
b1000 ,
b10 $
b10 (
0%
b11000100 &
#1970
b1001 !
b1001 ,
1%
b11000101 &
#1980
b1001 !
b1001 ,
b11 $
b11 (
0%
b11000110 &
#1990
1)
b1010 !
b1010 ,
1%
b11000111 &
#2000
0*
0)
b1010 !
b1010 ,
b100 $
b100 (
0%
b11001000 &
#2010
b1011 !
b1011 ,
1%
b11001001 &
#2020
b1011 !
b1011 ,
b101 $
b101 (
0%
b11001010 &
#2030
1*
1)
b1100 !
b1100 ,
1%
b11001011 &
#2040
0)
b1100 !
b1100 ,
b110 $
b110 (
0%
b11001100 &
#2050
b1101 !
b1101 ,
1%
b11001101 &
#2060
b1101 !
b1101 ,
b111 $
b111 (
0%
b11001110 &
#2070
1)
b1110 !
b1110 ,
1%
b11001111 &
#2080
0+
0"
0*
0)
b1110 !
b1110 ,
b1000 $
b1000 (
0%
b11010000 &
#2090
b1111 !
b1111 ,
1%
b11010001 &
#2100
b1111 !
b1111 ,
b1001 $
b1001 (
0%
b11010010 &
#2110
1"
1+
1*
1)
b0 !
b0 ,
1%
b11010011 &
#2120
0)
b0 !
b0 ,
b1010 $
b1010 (
0%
b11010100 &
#2130
b1 !
b1 ,
1%
b11010101 &
#2140
b1 !
b1 ,
b1011 $
b1011 (
0%
b11010110 &
#2150
1)
b10 !
b10 ,
1%
b11010111 &
#2160
0*
0)
b10 !
b10 ,
b1100 $
b1100 (
0%
b11011000 &
#2170
b11 !
b11 ,
1%
b11011001 &
#2180
b11 !
b11 ,
b1101 $
b1101 (
0%
b11011010 &
#2190
1*
1)
b100 !
b100 ,
1%
b11011011 &
#2200
0)
b100 !
b100 ,
b1110 $
b1110 (
0%
b11011100 &
#2210
b101 !
b101 ,
1%
b11011101 &
#2220
b101 !
b101 ,
b1111 $
b1111 (
0%
b11011110 &
#2230
1)
b110 !
b110 ,
1%
b11011111 &
#2240
0+
0"
0*
0)
b111 !
b111 ,
b111 #
b111 '
b0 $
b0 (
0%
b11100000 &
#2250
1+
1*
1)
b1000 !
b1000 ,
1%
b11100001 &
#2260
1+
1*
1)
b1000 !
b1000 ,
b1 $
b1 (
0%
b11100010 &
#2270
b1001 !
b1001 ,
1%
b11100011 &
#2280
0)
b1001 !
b1001 ,
b10 $
b10 (
0%
b11100100 &
#2290
1)
b1010 !
b1010 ,
1%
b11100101 &
#2300
1)
b1010 !
b1010 ,
b11 $
b11 (
0%
b11100110 &
#2310
b1011 !
b1011 ,
1%
b11100111 &
#2320
0*
0)
b1011 !
b1011 ,
b100 $
b100 (
0%
b11101000 &
#2330
1*
1)
b1100 !
b1100 ,
1%
b11101001 &
#2340
1*
1)
b1100 !
b1100 ,
b101 $
b101 (
0%
b11101010 &
#2350
b1101 !
b1101 ,
1%
b11101011 &
#2360
0)
b1101 !
b1101 ,
b110 $
b110 (
0%
b11101100 &
#2370
1)
b1110 !
b1110 ,
1%
b11101101 &
#2380
1)
b1110 !
b1110 ,
b111 $
b111 (
0%
b11101110 &
#2390
b1111 !
b1111 ,
1%
b11101111 &
#2400
0+
0*
0"
0)
b1111 !
b1111 ,
b1000 $
b1000 (
0%
b11110000 &
#2410
1"
1+
1*
1)
b0 !
b0 ,
1%
b11110001 &
#2420
1"
1+
1*
1)
b0 !
b0 ,
b1001 $
b1001 (
0%
b11110010 &
#2430
b1 !
b1 ,
1%
b11110011 &
#2440
0)
b1 !
b1 ,
b1010 $
b1010 (
0%
b11110100 &
#2450
1)
b10 !
b10 ,
1%
b11110101 &
#2460
1)
b10 !
b10 ,
b1011 $
b1011 (
0%
b11110110 &
#2470
b11 !
b11 ,
1%
b11110111 &
#2480
0*
0)
b11 !
b11 ,
b1100 $
b1100 (
0%
b11111000 &
#2490
1*
1)
b100 !
b100 ,
1%
b11111001 &
#2500
1*
1)
b100 !
b100 ,
b1101 $
b1101 (
0%
b11111010 &
#2510
b101 !
b101 ,
1%
b11111011 &
#2520
0)
b101 !
b101 ,
b1110 $
b1110 (
0%
b11111100 &
#2530
1)
b110 !
b110 ,
1%
b11111101 &
#2540
1)
b110 !
b110 ,
b1111 $
b1111 (
0%
b11111110 &
#2550
b111 !
b111 ,
1%
b11111111 &
#2560
b100000000 &
