3_Intermediate_Combinational/Odd_Even_Detector/odd_even_detector_beh.v
module odd_even_detector_beh #(parameter N=3)(input [N-1:0]a,output reg o,e);
always @ (*) begin
if(a[0]==0)begin
o=0;e=1;end
else begin
o=1;e=0;end
end
endmodule

3_Intermediate_Combinational/Odd_Even_Detector/odd_even_detector_tb.v
module odd_even_detector_tb;
reg [2:0]a;
wire o,e;

odd_even_detector_beh #(3) uut (.a(a),.o(o),.e(e));

integer i;

initial
begin
$dumpfile("odd_even_detector.vcd");
$dumpvars(0,odd_even_detector_tb);

$monitor("time=%0t,a=%b,odd=%b,even=%b",$time,a,o,e);

for(i=0;i<8;i=i+1)
begin
a=i;
#10;
end
end
endmodule

3_Intermediate_Combinational/Odd_Even_Detector/odd_even_detector.vcd
$date
	Wed Jun 17 04:21:40 2026
$end
$version
	Icarus Verilog
$end
$timescale
	1s
$end
$scope module odd_even_detector_tb $end
$var wire 1 ! o $end
$var wire 1 " e $end
$var reg 3 # a [2:0] $end
$var integer 32 $ i [31:0] $end
$scope module uut $end
$var wire 3 % a [2:0] $end
$var parameter 32 & N $end
$var reg 1 " e $end
$var reg 1 ! o $end
$upscope $end
$upscope $end
$enddefinitions $end
$comment Show the parameter values. $end
$dumpall
b11 &
$end
#0
$dumpvars
b0 %
b0 $
b0 #
1"
0!
$end
#10
0"
1!
b1 #
b1 %
b1 $
#20
1"
0!
b10 #
b10 %
b10 $
#30
0"
1!
b11 #
b11 %
b11 $
#40
1"
0!
b100 #
b100 %
b100 $
#50
0"
1!
b101 #
b101 %
b101 $
#60
1"
0!
b110 #
b110 %
b110 $
#70
0"
1!
b111 #
b111 %
b111 $
#80
b1000 $
