combinational/mux_2x1/mux_2x1_struct.v
module mux_2x1_struct (
    input  A, B, S,
    output Y
);
    wire S_bar, w1, w2;
    not  g1 (S_bar, S);
    and  g2 (w1, A, S_bar);
    and  g3 (w2, B, S);
    or   g4 (Y, w1, w2);
endmodule

combinational/mux_2x1/mux_2x1_tb.v
module mux_2x1_tb;
    reg  A, B, S;
    wire Y;

    mux_2x1_struct uut (
        .A(A),
	.B(B),
	.S(S),
	.Y(Y)
    );

    initial begin
	$dumpfile("mux_2x1.vcd");
	$dumpvars(0,mux_2x1_tb);
        $display("S  A  B | Y");
        $display("--------|--");
        {S, A, B} = 3'b000; #10; $display("%b  %b  %b | %b", S, A, B, Y);
        {S, A, B} = 3'b001; #10; $display("%b  %b  %b | %b", S, A, B, Y);
        {S, A, B} = 3'b010; #10; $display("%b  %b  %b | %b", S, A, B, Y);
        {S, A, B} = 3'b011; #10; $display("%b  %b  %b | %b", S, A, B, Y);
        {S, A, B} = 3'b100; #10; $display("%b  %b  %b | %b", S, A, B, Y);
        {S, A, B} = 3'b101; #10; $display("%b  %b  %b | %b", S, A, B, Y);
        {S, A, B} = 3'b110; #10; $display("%b  %b  %b | %b", S, A, B, Y);
        {S, A, B} = 3'b111; #10; $display("%b  %b  %b | %b", S, A, B, Y);
        $finish;
    end
endmodule

combinational/mux_2x1/mux_2x1.vcd
$date
	Fri Jun  5 02:37:22 2026
$end
$version
	Icarus Verilog
$end
$timescale
	1s
$end
$scope module mux_2x1_tb $end
$var wire 1 ! Y $end
$var reg 1 " A $end
$var reg 1 # B $end
$var reg 1 $ S $end
$scope module uut $end
$var wire 1 " A $end
$var wire 1 # B $end
$var wire 1 $ S $end
$var wire 1 % S_bar $end
$var wire 1 ! Y $end
$var wire 1 & w1 $end
$var wire 1 ' w2 $end
$upscope $end
$upscope $end
$enddefinitions $end
$comment Show the parameter values. $end
$dumpall
$end
#0
$dumpvars
0'
0&
1%
0$
0#
0"
0!
$end
#10
1#
#20
1!
1&
1"
0#
#30
1#
#40
0!
0%
0&
1$
0"
0#
#50
1!
1'
1#
#60
0!
0'
1"
0#
#70
1!
1'
1#
