FSM_project/improvised/lift_schedule.v
`timescale 1ns/1ps
 
 
module lift_schedule #( parameter FLOORS = 4, parameter MOVE_TICKS = 2, parameter DOOR_TICKS = 2)(
    input  wire              clk,
    input  wire              rst,
    input  wire [FLOORS-1:0] floor_request,
    input  wire              door_obstruction,
    input  wire              emergency_stop,
    output reg  [1:0]        current_floor,
    output reg               door_open,
    output reg               motor_up,
    output reg               motor_down,
    output wire [2:0]        state_dbg
);
    localparam S_IDLE             = 3'b000;
    localparam S_DOOR_OPEN        = 3'b001;
    localparam S_MOVE_UP          = 3'b010;
    localparam S_MOVE_DOWN        = 3'b011;
    localparam S_EMERGENCY_RESCUE = 3'b100;
    localparam S_EMERGENCY        = 3'b101;
 
    reg [2:0] state_q, state_d;
 
    reg [FLOORS-1:0] pending_q;
    reg [1:0]        move_timer;   // enough bits for MOVE_TICKS
    reg [1:0]        door_timer;   // enough bits for DOOR_TICKS
    reg              saved_dir;    // 1=was up, 0=was down
 
    reg               current_req, above_req, below_req;
    reg               move_done, door_done, nearest_floor_reached;
    reg [1:0]         next_floor_up, next_floor_dn;
    reg               next_cur_req_up, next_cur_req_dn;
    reg [FLOORS-1:0]  pending_new;
 
    integer i;
 
    always @(*) begin
        pending_new = pending_q | floor_request;
 
        current_req = pending_new[current_floor];
 
        above_req = 1'b0;
        below_req = 1'b0;
        for (i = 0; i < FLOORS; i = i + 1) begin
            if (i > current_floor) above_req = above_req | pending_new[i];
            if (i < current_floor) below_req = below_req | pending_new[i];
        end
 
        move_done             = (move_timer == MOVE_TICKS - 1);
        door_done             = (door_timer == DOOR_TICKS - 1) & ~door_obstruction;
        nearest_floor_reached = move_done;
 
        next_floor_up = current_floor + 1;
        next_floor_dn = current_floor - 1;
 
        
        next_cur_req_up = pending_new[next_floor_up];
        next_cur_req_dn = pending_new[next_floor_dn];
    end
 
    
    always @(*) begin
        state_d = state_q;
 
        case (state_q)
            S_IDLE: begin
                if      (emergency_stop) state_d = S_EMERGENCY;
                else if (current_req)    state_d = S_DOOR_OPEN;
                else if (above_req)      state_d = S_MOVE_UP;
                else if (below_req)      state_d = S_MOVE_DOWN;
            end
 
            S_MOVE_UP: begin
                if      (emergency_stop)                  state_d = S_EMERGENCY_RESCUE;
                else if (move_done & next_cur_req_up)     state_d = S_DOOR_OPEN;
            end
 
            S_MOVE_DOWN: begin
                if      (emergency_stop)                  state_d = S_EMERGENCY_RESCUE;
                else if (move_done & next_cur_req_dn)     state_d = S_DOOR_OPEN;
            end
 
            S_DOOR_OPEN: begin
                if      (emergency_stop)             state_d = S_EMERGENCY;
                else if (door_obstruction)           state_d = S_DOOR_OPEN;
                else if (door_done & above_req)      state_d = S_MOVE_UP;
                else if (door_done & below_req)      state_d = S_MOVE_DOWN;
                else if (door_done)                  state_d = S_IDLE;
            end
 
            S_EMERGENCY_RESCUE: begin
                if (nearest_floor_reached) state_d = S_EMERGENCY;
            end
 
            S_EMERGENCY: begin
                if (!emergency_stop) state_d = S_IDLE;
            end
 
            default: state_d = S_IDLE;
        endcase
    end
 
    always @(posedge clk) begin
        if (rst) begin
            state_q       <= S_IDLE;
            current_floor <= 2'b00;
            pending_q     <= {FLOORS{1'b0}};
            move_timer    <= 2'b00;
            door_timer    <= 2'b00;
            saved_dir     <= 1'b0;
        end else begin
           
            pending_q <= pending_q | floor_request;
 
            state_q <= state_d;
 
            case (state_q)
                S_MOVE_UP: begin
                    if (emergency_stop) begin
                        saved_dir  <= 1'b0;   // invert: rescue goes DOWN to lower floor
                        move_timer <= 2'b00;
                    end else if (move_done) begin
                        current_floor <= current_floor + 1;
                        move_timer    <= 2'b00;
                    end else begin
                        move_timer <= move_timer + 1;
                    end
                end
 
                S_MOVE_DOWN: begin
                    if (emergency_stop) begin
                        saved_dir  <= 1'b0;
                        move_timer <= 2'b00;
                    end else if (move_done) begin
                        current_floor <= current_floor - 1;
                        move_timer    <= 2'b00;
                    end else begin
                        move_timer <= move_timer + 1;
                    end
                end
 
                S_DOOR_OPEN: begin
                    if (!emergency_stop) begin
                        // Clear the serviced floor's request
                        pending_q[current_floor] <= 1'b0;
                        if (!door_obstruction)
                            door_timer <= door_timer + 1;
                    end
                    if (door_done) door_timer <= 2'b00;
                end
 
                S_EMERGENCY_RESCUE: begin
                    if (nearest_floor_reached) begin
                        current_floor <= saved_dir ?
                                         current_floor + 1 :
                                         current_floor - 1;
                        move_timer <= 2'b00;
                    end else begin
                        move_timer <= move_timer + 1;
                    end
                end
 
                default: begin
                    move_timer <= 2'b00;
                    door_timer <= 2'b00;
                end
            endcase
        end
    end
 
    
    always @(*) begin
        door_open  = 1'b0;
        motor_up   = 1'b0;
        motor_down = 1'b0;
 
        case (state_q)
            S_IDLE:             ; // all zero
            S_MOVE_UP:          motor_up   = 1'b1;
            S_MOVE_DOWN:        motor_down = 1'b1;
            S_DOOR_OPEN:        door_open  = 1'b1;
            S_EMERGENCY_RESCUE: begin
                motor_up   =  saved_dir;
                motor_down = ~saved_dir;
            end
            S_EMERGENCY:        door_open  = 1'b1;
            default:            ;
        endcase
    end
 
    assign state_dbg = state_q;
 
endmodule

FSM_project/lift_controller/lift_schedule_tb.v
`timescale 1ns/1ps

module lift_schedule_tb;

    reg        clk, rst;
    reg  [3:0] floor_request;
    reg        door_obstruction, emergency_stop;
    wire [1:0] current_floor;
    wire       door_open, motor_up, motor_down;
    wire [2:0] state_dbg;

    localparam MOVE_TICKS = 2;
    localparam DOOR_TICKS = 2;

    lift_schedule #(
        .FLOORS(4), .MOVE_TICKS(MOVE_TICKS), .DOOR_TICKS(DOOR_TICKS)
    ) dut (
        .clk(clk), .rst(rst),
        .floor_request(floor_request),
        .door_obstruction(door_obstruction),
        .emergency_stop(emergency_stop),
        .current_floor(current_floor),
        .door_open(door_open), .motor_up(motor_up), .motor_down(motor_down),
        .state_dbg(state_dbg)
    );

    initial clk = 0;
    always #5 clk = ~clk;

    initial begin
        $dumpfile("WAVEFORM");
        $dumpvars(0, lift_schedule_tb);
    end

    reg [7:0]  pass_count;
    reg [7:0]  fail_count;
    reg [7:0]  test_fail;
    integer    i;

    initial begin
        pass_count = 0;
        fail_count = 0;
        test_fail  = 0;

        $display("=== Lift Scheduling System ===");

        // ------------------------------------------------------------
        // TEST 1: Reset behaviour
        // ------------------------------------------------------------
        
        rst = 1; floor_request = 0; door_obstruction = 0; emergency_stop = 0;
        repeat(3) @(posedge clk); #1;
        rst = 0; // checking with floor request equal to 0, if rst = 1 then full sys freezes
        @(posedge clk); #1;

        
        if (state_dbg == 3'b000) pass_count = pass_count + 1;
        else begin fail_count = fail_count + 1; test_fail = test_fail + 1; end

        if (current_floor === 2'b00) pass_count = pass_count + 1;
        else begin fail_count = fail_count + 1; test_fail = test_fail + 1; end

        if (door_open === 1'b0) pass_count = pass_count + 1;
        else begin fail_count = fail_count + 1; test_fail = test_fail + 1; end

        if (motor_up === 1'b0) pass_count = pass_count + 1;
        else begin fail_count = fail_count + 1; test_fail = test_fail + 1; end

        if (motor_down === 1'b0) pass_count = pass_count + 1;
        else begin fail_count = fail_count + 1; test_fail = test_fail + 1; end

        if (test_fail == 0) $display("TEST 1 PASS"); else $display("TEST 1 FAIL");
        test_fail = 0;

        
        // TEST 2: Current floor request (floor 0)
        
        rst = 1; floor_request = 0; door_obstruction = 0; emergency_stop = 0; // rst all values
        repeat(3) @(posedge clk); #1;
        rst = 0;
        @(posedge clk); #1;

        @(negedge clk); floor_request = 4'b0001; emergency_stop = 0;
        repeat(2) @(posedge clk); #1;
        floor_request = 0;

        if (door_open === 1'b1) pass_count = pass_count + 1;
        else begin fail_count = fail_count + 1; test_fail = test_fail + 1; end

        if (motor_up === 1'b0) pass_count = pass_count + 1;
        else begin fail_count = fail_count + 1; test_fail = test_fail + 1; end

	if (motor_down === 1'b0) pass_count = pass_count + 1;
        else begin fail_count = fail_count + 1; test_fail = test_fail + 1; end

        repeat(DOOR_TICKS + 1) @(posedge clk); #1; // adding 1 to the closing time for safety margin

        if (state_dbg === 3'b000) pass_count = pass_count + 1;
        else begin fail_count = fail_count + 1; test_fail = test_fail + 1; end

        if (test_fail == 0) $display("TEST 2 PASS"); else $display("TEST 2 FAIL");
        test_fail = 0;

        
        // TEST 3: Upward service floors 1 and 2
        
        rst = 1; floor_request = 0; door_obstruction = 0; emergency_stop = 0;
        repeat(3) @(posedge clk); #1;
        rst = 0;
        @(posedge clk); #1;

        @(negedge clk); floor_request = 4'b0110; emergency_stop = 0;
        repeat(2) @(posedge clk); #1;
        floor_request = 0;

        if (motor_up === 1'b1) pass_count = pass_count + 1;
        else begin fail_count = fail_count + 1; test_fail = test_fail + 1; end

        repeat(MOVE_TICKS) @(posedge clk); #1;

        if (door_open === 1'b1) pass_count = pass_count + 1;
        else begin fail_count = fail_count + 1; test_fail = test_fail + 1; end

        if (current_floor === 2'b01) pass_count = pass_count + 1;
        else begin fail_count = fail_count + 1; test_fail = test_fail + 1; end

        @(posedge clk); #1;

        if (motor_up === 1'b1) pass_count = pass_count + 1;
        else begin fail_count = fail_count + 1; test_fail = test_fail + 1; end

        repeat(2) @(posedge clk); #1;

        if (door_open === 1'b1) pass_count = pass_count + 1;
        else begin fail_count = fail_count + 1; test_fail = test_fail + 1; end

        if (current_floor === 2'b10) pass_count = pass_count + 1;
        else begin fail_count = fail_count + 1; test_fail = test_fail + 1; end

        repeat(DOOR_TICKS + 2) @(posedge clk); #1;

        if (state_dbg === 3'b000) pass_count = pass_count + 1;
        else begin fail_count = fail_count + 1; test_fail = test_fail + 1; end

        if (test_fail == 0) $display("TEST 3 PASS"); else $display("TEST 3 FAIL");
        test_fail = 0;

        // ------------------------------------------------------------
        // TEST 4: Door obstruction
        // ------------------------------------------------------------
        rst = 1; floor_request = 0; door_obstruction = 0; emergency_stop = 0;
        repeat(3) @(posedge clk); #1;
        rst = 0;
        @(posedge clk); #1;

        @(negedge clk); floor_request = 4'b0001; emergency_stop = 0;
        repeat(2) @(posedge clk); #1;
        floor_request = 0;
        door_obstruction = 1;

        repeat(DOOR_TICKS + 3) @(posedge clk); #1;

        if (door_open === 1'b1) pass_count = pass_count + 1;
        else begin fail_count = fail_count + 1; test_fail = test_fail + 1; end

        door_obstruction = 0;
        repeat(DOOR_TICKS + 1) @(posedge clk); #1;

        if (door_open === 1'b0) pass_count = pass_count + 1;
        else begin fail_count = fail_count + 1; test_fail = test_fail + 1; end

        if (test_fail == 0) $display("TEST 4 PASS"); else $display("TEST 4 FAIL");
        test_fail = 0;

        // ------------------------------------------------------------
        // TEST 5: Downward service after upward
        // ------------------------------------------------------------
        rst = 1; floor_request = 0; door_obstruction = 0; emergency_stop = 0;
        repeat(3) @(posedge clk); #1;
        rst = 0;
        @(posedge clk); #1;

        @(negedge clk); floor_request = 4'b0100; emergency_stop = 0;
        repeat(2) @(posedge clk); #1;
        floor_request = 0;

        repeat(MOVE_TICKS) @(posedge clk); #1;
        repeat(MOVE_TICKS) @(posedge clk); #1;

        if (door_open === 1'b1) pass_count = pass_count + 1;
        else begin fail_count = fail_count + 1; test_fail = test_fail + 1; end

        if (current_floor === 2'b10) pass_count = pass_count + 1;
        else begin fail_count = fail_count + 1; test_fail = test_fail + 1; end

        @(negedge clk); floor_request = 4'b0001; emergency_stop = 0;
        @(posedge clk); #1;
        floor_request = 0;

        repeat(DOOR_TICKS + 1) @(posedge clk); #1;

        if (motor_down === 1'b1) pass_count = pass_count + 1;
        else begin fail_count = fail_count + 1; test_fail = test_fail + 1; end

        if (test_fail == 0) $display("TEST 5 PASS"); else $display("TEST 5 FAIL");
        test_fail = 0;

        // ------------------------------------------------------------
        // TEST 6: Emergency from IDLE
        // ------------------------------------------------------------
        rst = 1; floor_request = 0; door_obstruction = 0; emergency_stop = 0;
        repeat(3) @(posedge clk); #1;
        rst = 0;
        @(posedge clk); #1;

        @(negedge clk); floor_request = 0; emergency_stop = 1;
        repeat(2) @(posedge clk); #1;

        if (door_open === 1'b1) pass_count = pass_count + 1;
        else begin fail_count = fail_count + 1; test_fail = test_fail + 1; end

        if (motor_up === 1'b0) pass_count = pass_count + 1;
        else begin fail_count = fail_count + 1; test_fail = test_fail + 1; end

        if (motor_down === 1'b0) pass_count = pass_count + 1;
        else begin fail_count = fail_count + 1; test_fail = test_fail + 1; end

        if (state_dbg === 3'b101) pass_count = pass_count + 1;
        else begin fail_count = fail_count + 1; test_fail = test_fail + 1; end

        @(negedge clk); emergency_stop = 0;
        repeat(2) @(posedge clk); #1;

        if (state_dbg === 3'b000) pass_count = pass_count + 1;
        else begin fail_count = fail_count + 1; test_fail = test_fail + 1; end

        if (test_fail == 0) $display("TEST 6 PASS"); else $display("TEST 6 FAIL");
        test_fail = 0;

        // ------------------------------------------------------------
        // TEST 7: Emergency mid-travel
        // ------------------------------------------------------------
        rst = 1; floor_request = 0; door_obstruction = 0; emergency_stop = 0;
        repeat(3) @(posedge clk); #1;
        rst = 0;
        @(posedge clk); #1;

        @(negedge clk); floor_request = 4'b0100; emergency_stop = 0;
        repeat(2) @(posedge clk); #1;
        floor_request = 0;

        if (motor_up === 1'b1) pass_count = pass_count + 1;
        else begin fail_count = fail_count + 1; test_fail = test_fail + 1; end

        @(negedge clk); floor_request = 0; emergency_stop = 1;
        repeat(2) @(posedge clk); #1;

        if (state_dbg === 3'b100) pass_count = pass_count + 1;
        else begin fail_count = fail_count + 1; test_fail = test_fail + 1; end

        if (door_open === 1'b0) pass_count = pass_count + 1;
        else begin fail_count = fail_count + 1; test_fail = test_fail + 1; end

        repeat(MOVE_TICKS) @(posedge clk); #1;

        if (state_dbg === 3'b101) pass_count = pass_count + 1;
        else begin fail_count = fail_count + 1; test_fail = test_fail + 1; end

        if (door_open === 1'b1) pass_count = pass_count + 1;
        else begin fail_count = fail_count + 1; test_fail = test_fail + 1; end

        @(negedge clk); emergency_stop = 0;
        repeat(6) @(posedge clk); #1;

        if (state_dbg === 3'b000) pass_count = pass_count + 1;
        else begin fail_count = fail_count + 1; test_fail = test_fail + 1; end

        if (test_fail == 0) $display("TEST 7 PASS"); else $display("TEST 7 FAIL");
        test_fail = 0;

        // ------------------------------------------------------------
        // Final summary
        // ------------------------------------------------------------
        $display("==============================");
        if (fail_count == 0)
            $display("SUMMARY: PASS (%0d checks)", pass_count);
        else
            $display("SUMMARY: FAIL (%0d passed, %0d failed)", pass_count, fail_count);
        $display("==============================");
        $finish;
    end

    initial begin
        #200000;
        $display("TIMEOUT");
        $finish;
    end

endmodule

FSM_project/improvised/WAVEFORM.vcd
$date
	Wed Jun 24 11:47:47 2026
$end
$version
	Icarus Verilog
$end
$timescale
	1ps
$end
$scope module lift_schedule_tb $end
$var wire 3 ! state_dbg [2:0] $end
$var wire 1 " motor_up $end
$var wire 1 # motor_down $end
$var wire 1 $ door_open $end
$var wire 2 % current_floor [1:0] $end
$var parameter 32 & DOOR_TICKS $end
$var parameter 32 ' MOVE_TICKS $end
$var reg 1 ( clk $end
$var reg 1 ) door_obstruction $end
$var reg 1 * emergency_stop $end
$var reg 8 + fail_count [7:0] $end
$var reg 4 , floor_request [3:0] $end
$var reg 8 - pass_count [7:0] $end
$var reg 1 . rst $end
$var reg 8 / test_fail [7:0] $end
$scope module dut $end
$var wire 1 ( clk $end
$var wire 1 ) door_obstruction $end
$var wire 1 * emergency_stop $end
$var wire 4 0 floor_request [3:0] $end
$var wire 1 . rst $end
$var wire 3 1 state_dbg [2:0] $end
$var parameter 32 2 DOOR_TICKS $end
$var parameter 32 3 FLOORS $end
$var parameter 32 4 MOVE_TICKS $end
$var parameter 3 5 S_DOOR_OPEN $end
$var parameter 3 6 S_EMERGENCY $end
$var parameter 3 7 S_EMERGENCY_RESCUE $end
$var parameter 3 8 S_IDLE $end
$var parameter 3 9 S_MOVE_DOWN $end
$var parameter 3 : S_MOVE_UP $end
$var reg 1 ; above_req $end
$var reg 1 < below_req $end
$var reg 2 = current_floor [1:0] $end
$var reg 1 > current_req $end
$var reg 1 ? door_done $end
$var reg 1 $ door_open $end
$var reg 2 @ door_timer [1:0] $end
$var reg 1 # motor_down $end
$var reg 1 " motor_up $end
$var reg 1 A move_done $end
$var reg 2 B move_timer [1:0] $end
$var reg 1 C nearest_floor_reached $end
$var reg 1 D next_cur_req_dn $end
$var reg 1 E next_cur_req_up $end
$var reg 2 F next_floor_dn [1:0] $end
$var reg 2 G next_floor_up [1:0] $end
$var reg 4 H pending_new [3:0] $end
$var reg 4 I pending_q [3:0] $end
$var reg 1 J saved_dir $end
$var reg 3 K state_d [2:0] $end
$var reg 3 L state_q [2:0] $end
$var integer 32 M i [31:0] $end
$upscope $end
$upscope $end
$enddefinitions $end
$comment Show the parameter values. $end
$dumpall
b10 :
b11 9
b0 8
b100 7
b101 6
b1 5
b10 4
b100 3
b10 2
b10 '
b10 &
$end
#0
$dumpvars
b100 M
bx L
b0 K
xJ
bx I
bx H
bx G
bx F
xE
xD
xC
bx B
xA
bx @
x?
x>
bx =
0<
0;
bx 1
b0 0
b0 /
1.
b0 -
b0 ,
b0 +
0*
0)
0(
bx %
x$
x#
x"
bx !
$end
#5000
0D
0E
b11 F
b1 G
0C
0?
0A
b100 M
0>
b0 H
0#
0"
0$
0J
b0 @
b0 B
b0 I
b0 %
b0 =
b0 !
b0 1
b0 L
1(
#10000
0(
#15000
1(
#20000
0(
#25000
1(
#26000
0.
#30000
0(
#35000
1(
#36000
1.
b101 -
#40000
0(
#45000
1(
#50000
0(
#55000
1(
#60000
0(
#65000
1(
#66000
0.
#70000
0(
#75000
1(
#80000
b1 K
b100 M
1>
b1 H
b1 ,
b1 0
0(
#85000
1$
b100 M
b1 !
b1 1
b1 L
b1 I
1(
#90000
0(
#95000
b0 K
1?
b100 M
b1 @
b0 I
1(
#96000
b0 K
b100 M
0>
b0 H
b1000 -
b0 ,
b0 0
#100000
0(
#105000
0?
b100 M
0$
b0 @
b0 !
b0 1
b0 L
1(
#110000
0(
#115000
1(
#120000
0(
#125000
1(
#126000
1.
b1001 -
#130000
0(
#135000
1(
#140000
0(
#145000
1(
#150000
0(
#155000
1(
#156000
0.
#160000
0(
#165000
1(
#170000
b10 K
1E
1;
b100 M
b110 H
b110 ,
b110 0
0(
#175000
1"
b100 M
1;
b10 !
b10 1
b10 L
b110 I
1(
#180000
0(
#185000
b1 K
1C
1A
b100 M
1;
b1 B
1(
#186000
b1 K
b100 M
1;
b1010 -
b0 ,
b0 0
#190000
0(
#195000
b0 F
b10 G
0C
0A
b100 M
1;
1>
1$
0"
b0 B
b1 %
b1 =
b1 !
b1 1
b1 L
1(
#200000
0(
#205000
b10 K
1?
b100 M
1;
0>
b100 H
b1 @
b100 I
1(
#206000
b1100 -
#210000
0(
#215000
0?
b100 M
1;
1"
0$
b0 @
b10 !
b10 1
b10 L
1(
#216000
b1101 -
#220000
0(
#225000
b1 K
1C
1A
b100 M
1;
b1 B
1(
#230000
0(
#235000
0E
b1 F
b11 G
0C
0A
b100 M
0;
1>
1$
0"
b0 B
b10 %
b10 =
b1 !
b1 1
b1 L
1(
#236000
b1111 -
#240000
0(
#245000
b0 K
1?
b100 M
0>
b0 H
b1 @
b0 I
1(
#250000
0(
#255000
0?
b100 M
0$
b0 @
b0 !
b0 1
b0 L
1(
#260000
0(
#265000
1(
#270000
0(
#275000
1(
#276000
1.
b10000 -
#280000
0(
#285000
b11 F
b1 G
b100 M
b0 %
b0 =
1(
#290000
0(
#295000
1(
#300000
0(
#305000
1(
#306000
0.
#310000
0(
#315000
1(
#320000
b1 K
b100 M
1>
b1 H
b1 ,
b1 0
0(
#325000
1$
b100 M
b1 !
b1 1
b1 L
b1 I
1(
#330000
0(
#335000
b0 K
1?
b100 M
b1 @
b0 I
1(
#336000
b1 K
0?
b100 M
0>
b0 H
1)
b0 ,
b0 0
#340000
0(
#345000
1(
#350000
0(
#355000
1(
#360000
0(
#365000
1(
#370000
0(
#375000
1(
#380000
0(
#385000
1(
#386000
b0 K
1?
b100 M
0)
b10001 -
#390000
0(
#395000
0?
b100 M
0$
b0 @
b0 !
b0 1
b0 L
1(
#400000
0(
#405000
1(
#410000
0(
#415000
1(
#416000
1.
b10010 -
#420000
0(
#425000
1(
#430000
0(
#435000
1(
#440000
0(
#445000
1(
#446000
0.
#450000
0(
#455000
1(
#460000
b10 K
1;
b100 M
b100 H
b100 ,
b100 0
0(
#465000
1"
b100 M
1;
b10 !
b10 1
b10 L
b100 I
1(
#470000
0(
#475000
1C
1A
b100 M
1;
b1 B
1(
#476000
b100 M
1;
b0 ,
b0 0
#480000
0(
#485000
1E
b0 F
b10 G
0C
0A
b100 M
1;
b0 B
b1 %
b1 =
1(
#490000
0(
#495000
b1 K
1C
1A
b100 M
1;
b1 B
1(
#500000
0(
#505000
0E
b1 F
b11 G
0C
0A
b100 M
0;
1>
1$
0"
b0 B
b10 %
b10 =
b1 !
b1 1
b1 L
1(
#510000
0(
#515000
b0 K
1?
b100 M
0>
b0 H
b1 @
b0 I
1(
#516000
b10100 -
#520000
b11 K
1<
b100 M
b1 H
b1 ,
b1 0
0(
#525000
1#
0$
0?
b100 M
1<
b0 @
b11 !
b11 1
b11 L
b1 I
1(
#526000
b100 M
1<
b0 ,
b0 0
#530000
0(
#535000
1C
1A
b100 M
1<
b1 B
1(
#540000
0(
#545000
1D
b0 F
b10 G
0C
0A
b100 M
1<
b0 B
b1 %
b1 =
1(
#550000
0(
#555000
b1 K
1C
1A
b100 M
1<
b1 B
1(
#556000
1.
b10101 -
#560000
0(
#565000
0D
b11 F
b1 G
0C
0A
b100 M
0<
b0 H
0#
b0 K
b0 B
b0 I
b0 %
b0 =
b0 !
b0 1
b0 L
1(
#570000
0(
#575000
1(
#580000
0(
#585000
1(
#586000
0.
#590000
0(
#595000
1(
#600000
b101 K
1*
0(
#605000
1$
b101 !
b101 1
b101 L
1(
#610000
0(
#615000
1(
#616000
b11001 -
#620000
b0 K
0*
0(
#625000
0$
b0 !
b0 1
b0 L
1(
#630000
0(
#635000
1(
#636000
1.
b11010 -
#640000
0(
#645000
1(
#650000
0(
#655000
1(
#660000
0(
#665000
1(
#666000
0.
#670000
0(
#675000
1(
#680000
b10 K
1;
b100 M
b100 H
b100 ,
b100 0
0(
#685000
1"
b100 M
1;
b10 !
b10 1
b10 L
b100 I
1(
#690000
0(
#695000
1C
1A
b100 M
1;
b1 B
1(
#696000
b100 M
1;
b11011 -
b0 ,
b0 0
#700000
b100 K
1*
0(
#705000
0C
0A
b100 M
1;
1#
0"
b100 K
b0 B
b100 !
b100 1
b100 L
1(
#710000
0(
#715000
b101 K
1C
1A
b100 M
1;
b1 B
1(
#716000
b11101 -
#720000
0(
#725000
1D
b10 F
b0 G
0C
0A
1<
b100 M
0;
1$
0#
b0 B
b11 %
b11 =
b101 !
b101 1
b101 L
1(
#730000
0(
#735000
1(
#736000
b11111 -
#740000
b0 K
0*
0(
#745000
0$
b11 K
b0 !
b0 1
b0 L
1(
#750000
0(
#755000
1#
b11 !
b11 1
b11 L
1(
#760000
0(
#765000
b1 K
1C
1A
b100 M
1<
b1 B
1(
#770000
0(
#775000
0D
b1 F
b11 G
0C
0A
b100 M
0<
1>
1$
0#
b0 B
b10 %
b10 =
b1 !
b1 1
b1 L
1(
#780000
0(
#785000
b0 K
1?
b100 M
0>
b0 H
b1 @
b0 I
1(
#790000
0(
#795000
0?
b100 M
0$
b0 @
b0 !
b0 1
b0 L
1(
#796000
b100000 -
