3_Intermediate_Combinational/Parity_Generator/Parity_Generator_behavioural_if.v
module Parity_Generator_behavioural_if(input a,b,c,output reg p);
always @ (*) begin
if(a^b^c)
p=1'b1;
else
p=1'b0;
end
endmodule

3_Intermediate_Combinational/Parity_Generator/Parity_Generator_tb.v
module Parity_Generator_tb;
reg a,b,c;
wire p;

Parity_Generator_behavioural_if uut(.a(a),.b(b),.c(c),.p(p));

integer i;

initial
begin
$dumpfile("Parity_Generator.vcd");
$dumpvars(0,Parity_Generator_tb);

for(i=0;i<8;i=i+1)
begin
{a,b,c}=i;
$display("time=%0t,a=%b,b=%b,c=%b | p=%b",$time,a,b,c,p);
#10;
end
end
endmodule

3_Intermediate_Combinational/Parity_Generator/Parity_Generator.vcd
$date
	Tue Jun 16 10:11:09 2026
$end
$version
	Icarus Verilog
$end
$timescale
	1s
$end
$scope module Parity_Generator_tb $end
$var wire 1 ! p $end
$var reg 1 " a $end
$var reg 1 # b $end
$var reg 1 $ c $end
$var integer 32 % i [31:0] $end
$scope module uut $end
$var wire 1 " a $end
$var wire 1 # b $end
$var wire 1 $ c $end
$var reg 1 ! p $end
$upscope $end
$upscope $end
$enddefinitions $end
$comment Show the parameter values. $end
$dumpall
$end
#0
$dumpvars
b0 %
0$
0#
0"
0!
$end
#10
1!
1$
b1 %
#20
1#
0$
b10 %
#30
0!
1$
b11 %
#40
1!
1"
0#
0$
b100 %
#50
0!
1$
b101 %
#60
1#
0$
b110 %
#70
1!
1$
b111 %
#80
b1000 %
