combinational/demux_1x4/demux_1x4_struct.v
module demux_1x4_struct(
input I,
input Select1,
input Select0,
output Y0,
output Y1,
output Y2,
output Y3
);

wire S1_bar,S0_bar;

not g1(S1_bar,Select1);
not g2(S0_bar,Select0);

and g3(Y0,I,S1_bar,S0_bar);
and g4(Y1,I,S1_bar,Select0);
and g5(Y2,I,Select1,S0_bar);
and g6(Y3,I,Select1,Select0);

endmodule

2_combinational/demux_1x4/demux_1x4_tb.v
module demux_1x4_tb;

reg I,Select1,Select0;
wire Y0,Y1,Y2,Y3;

demux_1x4_struct uut(
.I(I),
.Select1(Select1),
.Select0(Select0),
.Y0(Y0),
.Y1(Y1),
.Y2(Y2),
.Y3(Y3)
);

initial begin

$dumpfile("demux_1x4.vcd");
$dumpvars(0,demux_1x4_tb);

$display("I S1 S0 | Y0 Y1 Y2 Y3");

I=0; Select1=0; Select0=0;
#10;
$display("%b %b %b | %b %b %b %b",I,Select1,Select0,Y0,Y1,Y2,Y3);

I=0; Select1=0; Select0=1;
#10;
$display("%b %b %b | %b %b %b %b",I,Select1,Select0,Y0,Y1,Y2,Y3);

I=0; Select1=1; Select0=0;
#10;
$display("%b %b %b | %b %b %b %b",I,Select1,Select0,Y0,Y1,Y2,Y3);

I=0; Select1=1; Select0=1;
#10;
$display("%b %b %b | %b %b %b %b",I,Select1,Select0,Y0,Y1,Y2,Y3);

I=1; Select1=0; Select0=0;
#10;
$display("%b %b %b | %b %b %b %b",I,Select1,Select0,Y0,Y1,Y2,Y3);

I=1; Select1=0; Select0=1;
#10;
$display("%b %b %b | %b %b %b %b",I,Select1,Select0,Y0,Y1,Y2,Y3);

I=1; Select1=1; Select0=0;
#10;
$display("%b %b %b | %b %b %b %b",I,Select1,Select0,Y0,Y1,Y2,Y3);

I=1; Select1=1; Select0=1;
#10;
$display("%b %b %b | %b %b %b %b",I,Select1,Select0,Y0,Y1,Y2,Y3);

$finish;

end

endmodule

2_combinational/demux_1x4/demux_1x4.vcd
$date
	Tue Jun  9 00:53:20 2026
$end
$version
	Icarus Verilog
$end
$timescale
	1s
$end
$scope module demux_1x4_tb $end
$var wire 1 ! Y3 $end
$var wire 1 " Y2 $end
$var wire 1 # Y1 $end
$var wire 1 $ Y0 $end
$var reg 1 % I $end
$var reg 1 & Select0 $end
$var reg 1 ' Select1 $end
$scope module uut $end
$var wire 1 % I $end
$var wire 1 ( S0_bar $end
$var wire 1 ) S1_bar $end
$var wire 1 & Select0 $end
$var wire 1 ' Select1 $end
$var wire 1 $ Y0 $end
$var wire 1 # Y1 $end
$var wire 1 " Y2 $end
$var wire 1 ! Y3 $end
$upscope $end
$upscope $end
$enddefinitions $end
$comment Show the parameter values. $end
$dumpall
$end
#0
$dumpvars
1)
1(
0'
0&
0%
0$
0#
0"
0!
$end
#10
0(
1&
#20
1(
0)
0&
1'
#30
0(
1&
#40
1$
1(
1)
0&
0'
1%
#50
0$
0(
1#
1&
#60
1"
1(
0#
0)
0&
1'
#70
0"
0(
1!
1&
