combinational/encoder_8x3/encoder_8x3_struct.v
module encoder_8x3_struct(
input D0,D1,D2,D3,D4,D5,D6,D7,
output Y0,Y1,Y2
);

or g1(Y0,D1,D3,D5,D7);

or g2(Y1,D2,D3,D6,D7);

or g3(Y2,D4,D5,D6,D7);

endmodule

2_combinational/encoder_8x3/encoder_8x3_tb.v
module encoder_8x3_tb;

reg D0,D1,D2,D3,D4,D5,D6,D7;
wire Y0,Y1,Y2;

encoder_8x3_struct uut(
.D0(D0),
.D1(D1),
.D2(D2),
.D3(D3),
.D4(D4),
.D5(D5),
.D6(D6),
.D7(D7),
.Y0(Y0),
.Y1(Y1),
.Y2(Y2)
);

initial begin

$dumpfile("encoder_8x3.vcd");
$dumpvars(0,encoder_8x3_tb);

$display("D7 D6 D5 D4 D3 D2 D1 D0 | Y2 Y1 Y0");

D7=0;D6=0;D5=0;D4=0;D3=0;D2=0;D1=0;D0=1;
#10;
$display("%b %b %b %b %b %b %b %b | %b %b %b",D7,D6,D5,D4,D3,D2,D1,D0,Y2,Y1,Y0);

D7=0;D6=0;D5=0;D4=0;D3=0;D2=0;D1=1;D0=0;
#10;
$display("%b %b %b %b %b %b %b %b | %b %b %b",D7,D6,D5,D4,D3,D2,D1,D0,Y2,Y1,Y0);

D7=0;D6=0;D5=0;D4=0;D3=0;D2=1;D1=0;D0=0;
#10;
$display("%b %b %b %b %b %b %b %b | %b %b %b",D7,D6,D5,D4,D3,D2,D1,D0,Y2,Y1,Y0);

D7=0;D6=0;D5=0;D4=0;D3=1;D2=0;D1=0;D0=0;
#10;
$display("%b %b %b %b %b %b %b %b | %b %b %b",D7,D6,D5,D4,D3,D2,D1,D0,Y2,Y1,Y0);

D7=0;D6=0;D5=0;D4=1;D3=0;D2=0;D1=0;D0=0;
#10;
$display("%b %b %b %b %b %b %b %b | %b %b %b",D7,D6,D5,D4,D3,D2,D1,D0,Y2,Y1,Y0);

D7=0;D6=0;D5=1;D4=0;D3=0;D2=0;D1=0;D0=0;
#10;
$display("%b %b %b %b %b %b %b %b | %b %b %b",D7,D6,D5,D4,D3,D2,D1,D0,Y2,Y1,Y0);

D7=0;D6=1;D5=0;D4=0;D3=0;D2=0;D1=0;D0=0;
#10;
$display("%b %b %b %b %b %b %b %b | %b %b %b",D7,D6,D5,D4,D3,D2,D1,D0,Y2,Y1,Y0);

D7=1;D6=0;D5=0;D4=0;D3=0;D2=0;D1=0;D0=0;
#10;
$display("%b %b %b %b %b %b %b %b | %b %b %b",D7,D6,D5,D4,D3,D2,D1,D0,Y2,Y1,Y0);

$finish;

end

endmodule

combinational/encoder_8x3/encoder_8x3.vcd
$date
	Tue Jun  9 01:18:07 2026
$end
$version
	Icarus Verilog
$end
$timescale
	1s
$end
$scope module encoder_8x3_tb $end
$var wire 1 ! Y2 $end
$var wire 1 " Y1 $end
$var wire 1 # Y0 $end
$var reg 1 $ D0 $end
$var reg 1 % D1 $end
$var reg 1 & D2 $end
$var reg 1 ' D3 $end
$var reg 1 ( D4 $end
$var reg 1 ) D5 $end
$var reg 1 * D6 $end
$var reg 1 + D7 $end
$scope module uut $end
$var wire 1 $ D0 $end
$var wire 1 % D1 $end
$var wire 1 & D2 $end
$var wire 1 ' D3 $end
$var wire 1 ( D4 $end
$var wire 1 ) D5 $end
$var wire 1 * D6 $end
$var wire 1 + D7 $end
$var wire 1 # Y0 $end
$var wire 1 " Y1 $end
$var wire 1 ! Y2 $end
$upscope $end
$upscope $end
$enddefinitions $end
$comment Show the parameter values. $end
$dumpall
$end
#0
$dumpvars
0+
0*
0)
0(
0'
0&
0%
1$
0#
0"
0!
$end
#10
1#
0$
1%
#20
0#
1"
0%
1&
#30
1#
0&
1'
#40
0#
0"
1!
0'
1(
#50
1#
0(
1)
#60
0#
1"
0)
1*
#70
1#
0*
1+
