3_Intermediate_Combinational/BCD_Adder/BCD_adder_data_always_case.v
module BCD_adder_data_always_case(input [3:0]a,b,input cin,output reg [3:0]s,output reg cout);
reg [4:0]temp;

always @(*) begin
temp=a+b+cin;

case(temp>5'd9)
1'b1: temp=temp+5'd6;
1'b0: temp=temp;

endcase

s=temp[3:0];
cout=temp[4];
end
endmodule

3_Intermediate_Combinational/BCD_Adder/BCD_adder_tb.v
module BCD_adder_tb;
reg [3:0]a,b;
reg cin;

wire [3:0]s;
wire cout;

BCD_adder_data_always_case uut(.a(a),.b(b),.s(s),.cin(cin),.cout(cout));

integer i;
initial
begin
$dumpfile("BCD_adder.vcd");
$dumpvars(0,BCD_adder_tb);

$monitor("time=%0t,a=%b,b=%b,cin=%b,cout=%b,s=%b",$time,a,b,cin,cout,s);

for(i=0;i<100;i=i+1)begin
a = $unsigned($random) % 10;
b = $unsigned($random) % 10;
cin = $unsigned($random) % 2;
#10;
end

$finish;
end
endmodule

3_Intermediate_Combinational/BCD_Adder/BCD_adder.vcd
$date
	Mon Jun 15 09:06:08 2026
$end
$version
	Icarus Verilog
$end
$timescale
	1s
$end
$scope module BCD_adder_tb $end
$var wire 4 ! s [3:0] $end
$var wire 1 " cout $end
$var reg 4 # a [3:0] $end
$var reg 4 $ b [3:0] $end
$var reg 1 % cin $end
$var integer 32 & i [31:0] $end
$scope module uut $end
$var wire 4 ' a [3:0] $end
$var wire 4 ( b [3:0] $end
$var wire 1 % cin $end
$var reg 1 " cout $end
$var reg 4 ) s [3:0] $end
$var reg 5 * temp [4:0] $end
$upscope $end
$upscope $end
$enddefinitions $end
$comment Show the parameter values. $end
$dumpall
$end
#0
$dumpvars
b10110 *
b110 )
b111 (
b1000 '
b0 &
1%
b111 $
b1000 #
1"
b110 !
$end
#10
b101 !
b101 )
b10101 *
b111 #
b111 '
b1 &
#20
0"
b1000 !
b1000 )
b1000 *
b10 $
b10 (
b101 #
b101 '
b10 &
#30
1"
b11000 *
b1000 $
b1000 (
b1001 #
b1001 '
b11 &
#40
b10 !
b10 )
b10010 *
b10 $
b10 (
b100 &
#50
b11 !
b11 )
b10011 *
0%
b111 $
b111 (
b110 #
b110 '
b101 &
#60
b0 !
b0 )
b10000 *
b101 $
b101 (
b101 #
b101 '
b110 &
#70
b101 !
b101 )
b10101 *
b110 $
b110 (
b1001 #
b1001 '
b111 &
#80
b1 !
b1 )
b10001 *
b11 $
b11 (
b1000 #
b1000 '
b1000 &
#90
b11 !
b11 )
b10011 *
1%
b1001 $
b1001 (
b11 #
b11 '
b1001 &
#100
0"
b11 *
0%
b0 $
b0 (
b1010 &
#110
1"
b1 !
b1 )
b10001 *
1%
b100 $
b100 (
b110 #
b110 '
b1011 &
#120
0"
b100 !
b100 )
b100 *
b1 $
b1 (
b10 #
b10 '
b1100 &
#130
b1001 !
b1001 )
b1001 *
b101 $
b101 (
b11 #
b11 '
b1101 &
#140
1"
b1 !
b1 )
b10001 *
b10 $
b10 (
b1000 #
b1000 '
b1110 &
#150
b110 !
b110 )
b10110 *
0%
b111 $
b111 (
b1001 #
b1001 '
b1111 &
#160
b100 !
b100 )
b10100 *
b1000 $
b1000 (
b110 #
b110 '
b10000 &
#170
0"
b111 !
b111 )
b111 *
b111 $
b111 (
b0 #
b0 '
b10001 &
#180
1"
b0 !
b0 )
b10000 *
1%
b1001 $
b1001 (
b10010 &
#190
b10 !
b10 )
b10010 *
0%
b110 $
b110 (
b110 #
b110 '
b10011 &
#200
0"
b1001 !
b1001 )
b1001 *
1%
b100 $
b100 (
b100 #
b100 '
b10100 &
#210
b101 !
b101 )
b101 *
b1 $
b1 (
b11 #
b11 '
b10101 &
#220
0%
b100 $
b100 (
b1 #
b1 '
b10110 &
#230
1%
b11 $
b11 (
b10111 &
#240
1"
b11 !
b11 )
b10011 *
b1000 $
b1000 (
b100 #
b100 '
b11000 &
#250
0"
b110 !
b110 )
b110 *
b0 $
b0 (
b101 #
b101 '
b11001 &
#260
b1000 !
b1000 )
b1000 *
b100 $
b100 (
b11 #
b11 '
b11010 &
#270
0%
b1 $
b1 (
b111 #
b111 '
b11011 &
#280
b110 !
b110 )
b110 *
b101 $
b101 (
b1 #
b1 '
b11100 &
#290
b1000 !
b1000 )
b1000 *
b100 $
b100 (
b100 #
b100 '
b11101 &
#300
b110 !
b110 )
b110 *
b101 $
b101 (
b1 #
b1 '
b11110 &
#310
b100 !
b100 )
b100 *
1%
b1 $
b1 (
b10 #
b10 '
b11111 &
#320
1"
b101 !
b101 )
b10101 *
b101 $
b101 (
b1001 #
b1001 '
b100000 &
#330
0"
b1000 !
b1000 )
b1000 *
b11 $
b11 (
b100 #
b100 '
b100001 &
#340
b11 !
b11 )
b11 *
0%
b0 $
b0 (
b11 #
b11 '
b100010 &
#350
1"
b10 !
b10 )
b10010 *
b100 $
b100 (
b1000 #
b1000 '
b100011 &
#360
b101 !
b101 )
b10101 *
1%
b1000 $
b1000 (
b110 #
b110 '
b100100 &
#370
b1 !
b1 )
b10001 *
b1001 $
b1001 (
b1 #
b1 '
b100101 &
#380
b100 !
b100 )
b10100 *
b110 $
b110 (
b111 #
b111 '
b100110 &
#390
0"
b1001 !
b1001 )
b1001 *
0%
b1000 $
b1000 (
b1 #
b1 '
b100111 &
#400
1"
b0 !
b0 )
b10000 *
b1001 $
b1001 (
b101000 &
#410
0"
b1001 !
b1001 )
b1001 *
1%
b11 $
b11 (
b101 #
b101 '
b101001 &
#420
1"
b11 !
b11 )
b10011 *
0%
b110 $
b110 (
b111 #
b111 '
b101010 &
#430
b10011 *
b101 $
b101 (
b1000 #
b1000 '
b101011 &
#440
b10011 *
1%
b110 $
b110 (
b110 #
b110 '
b101100 &
#450
0"
b11 *
0%
b0 $
b0 (
b11 #
b11 '
b101101 &
#460
1"
b1 !
b1 )
b10001 *
b100 $
b100 (
b111 #
b111 '
b101110 &
#470
0"
b1001 !
b1001 )
b1001 *
b101 $
b101 (
b100 #
b100 '
b101111 &
#480
b101 !
b101 )
b101 *
b1 $
b1 (
b110000 &
#490
b11 !
b11 )
b11 *
1%
b1 #
b1 '
b110001 &
#500
1"
b10 !
b10 )
b10010 *
0%
b11 $
b11 (
b1001 #
b1001 '
b110010 &
#510
0"
b111 !
b111 )
b111 *
1%
b110 $
b110 (
b0 #
b0 '
b110011 &
#520
b1001 !
b1001 )
b1001 *
b10 $
b10 (
b110 #
b110 '
b110100 &
#530
b101 !
b101 )
b101 *
0%
b100 $
b100 (
b1 #
b1 '
b110101 &
#540
1"
b0 !
b0 )
b10000 *
1%
b11 $
b11 (
b110 #
b110 '
b110110 &
#550
0"
b10 !
b10 )
b10 *
0%
b10 $
b10 (
b0 #
b0 '
b110111 &
#560
b110 !
b110 )
b110 *
b1 $
b1 (
b101 #
b101 '
b111000 &
#570
b11 !
b11 )
b11 *
1%
b0 $
b0 (
b10 #
b10 '
b111001 &
#580
1"
b1 !
b1 )
b10001 *
b10 $
b10 (
b1000 #
b1000 '
b111010 &
#590
0"
b1000 !
b1000 )
b1000 *
0%
b1000 $
b1000 (
b0 #
b0 '
b111011 &
#600
b110 !
b110 )
b110 *
1%
b100 $
b100 (
b1 #
b1 '
b111100 &
#610
1"
b11 !
b11 )
b10011 *
0%
b1001 #
b1001 '
b111101 &
#620
b1 !
b1 )
b10001 *
1%
b10 $
b10 (
b1000 #
b1000 '
b111110 &
#630
0"
b0 !
b0 )
b0 *
0%
b0 $
b0 (
b0 #
b0 '
b111111 &
#640
1"
b10000 *
1%
b101 $
b101 (
b100 #
b100 '
b1000000 &
#650
0"
b1000 !
b1000 )
b1000 *
b110 $
b110 (
b1 #
b1 '
b1000001 &
#660
1"
b0 !
b0 )
b10000 *
0%
b1001 $
b1001 (
b1000010 &
#670
0"
b100 !
b100 )
b100 *
1%
b1 $
b1 (
b10 #
b10 '
b1000011 &
#680
b101 !
b101 )
b101 *
b11 $
b11 (
b1 #
b1 '
b1000100 &
#690
b110 !
b110 )
b110 *
b10 #
b10 '
b1000101 &
#700
b1000 !
b1000 )
b1000 *
0%
b10 $
b10 (
b110 #
b110 '
b1000110 &
#710
1"
b11000 *
1%
b1001 $
b1001 (
b1000 #
b1000 '
b1000111 &
#720
0"
b101 !
b101 )
b101 *
b10 $
b10 (
b10 #
b10 '
b1001000 &
#730
b1001 !
b1001 )
b1001 *
b110 #
b110 '
b1001001 &
#740
1"
b1 !
b1 )
b10001 *
b110 $
b110 (
b100 #
b100 '
b1001010 &
#750
0"
b101 !
b101 )
b101 *
b10 $
b10 (
b10 #
b10 '
b1001011 &
#760
b100 !
b100 )
b100 *
0%
b11 $
b11 (
b1 #
b1 '
b1001100 &
#770
b1001 !
b1001 )
b1001 *
1%
b10 $
b10 (
b110 #
b110 '
b1001101 &
#780
b11 !
b11 )
b11 *
b0 $
b0 (
b10 #
b10 '
b1001110 &
#790
b1000 !
b1000 )
b1000 *
0%
b100 $
b100 (
b100 #
b100 '
b1001111 &
#800
b11 !
b11 )
b11 *
b1 $
b1 (
b10 #
b10 '
b1010000 &
#810
b101 !
b101 )
b101 *
1%
b10 $
b10 (
b1010001 &
#820
1"
b0 !
b0 )
b10000 *
b1000 $
b1000 (
b1 #
b1 '
b1010010 &
#830
0"
b1001 !
b1001 )
b1001 *
b101 $
b101 (
b11 #
b11 '
b1010011 &
#840
1"
b100 !
b100 )
b10100 *
b111 $
b111 (
b110 #
b110 '
b1010100 &
#850
0"
b111 !
b111 )
b111 *
0%
b110 $
b110 (
b1 #
b1 '
b1010101 &
#860
b1001 !
b1001 )
b1001 *
b0 $
b0 (
b1001 #
b1001 '
b1010110 &
#870
b110 !
b110 )
b110 *
b101 $
b101 (
b1 #
b1 '
b1010111 &
#880
b101 !
b101 )
b101 *
b11 $
b11 (
b10 #
b10 '
b1011000 &
#890
1"
b10101 *
b1001 $
b1001 (
b110 #
b110 '
b1011001 &
#900
b0 !
b0 )
b10000 *
b111 $
b111 (
b11 #
b11 '
b1011010 &
#910
0"
b10 !
b10 )
b10 *
1%
b0 $
b0 (
b1 #
b1 '
b1011011 &
#920
b101 !
b101 )
b101 *
b100 #
b100 '
b1011100 &
#930
b1000 !
b1000 )
b1000 *
0%
b110 $
b110 (
b10 #
b10 '
b1011101 &
#940
b1001 !
b1001 )
b1001 *
1%
b11 $
b11 (
b101 #
b101 '
b1011110 &
#950
b110 !
b110 )
b110 *
0%
b101 $
b101 (
b1 #
b1 '
b1011111 &
#960
1"
b11 !
b11 )
b10011 *
1%
b11 $
b11 (
b1001 #
b1001 '
b1100000 &
#970
0"
b1000 !
b1000 )
b1000 *
0%
b10 $
b10 (
b110 #
b110 '
b1100001 &
#980
b10 !
b10 )
b10 *
b0 $
b0 (
b10 #
b10 '
b1100010 &
#990
1"
b1 !
b1 )
b10001 *
1%
b1001 $
b1001 (
b1 #
b1 '
b1100011 &
#1000
b1100100 &
